Workbook

Sheet CE (ООО)
K1: ИТОГО, ДО НДС | M1: =M67 -> 0 | O1: IN COST | P1: ЦЕЛЬ | R1: 0.2 | S1: МАРЖ–ТЬ (ПЛАН) | T1: =X72 -> #DIV/0! | U1: IN-COST (ПЛАН) | V1: =X64 -> 0 | X1: МАРЖ-ТЬ (ФАКТ) | Y1: =AA72 -> #DIV/0! | Z1: IN-COST (ФАКТ) | AA1: =AA67 -> 0
C2: Название проекта | E2: кол-во | F2: наименование единицы | G2: единица | H2: цена за единицу | I2: переработки (всего) | K2: подытог | L2: налоговая ставка | M2: итого c налогами | N2: комментарии | P2: кол-во | Q2: наименование единицы | R2: единица | S2: цена за единицу | T2: переработки (всего) | V2: подытог (ПЛАН) | W2: Налоговая ставка | X2: Итого c налогами (ПЛАН) | Y2: подытог (ФАКТ) | Z2: налог | AA2: Итого c налогами (ФАКТ)
I4: часы | J4: ставка | T4: часы | U4: ставка
A7: A. РАЗРАБОТКА
B8: Разработка креатива | E8: 1 | F8: проект | G8: 1 | K8: =(E8*G8*H8)+(I8*J8*E8*G8) -> 0 | L8: 0.09 | M8: =K8/(1-L8) -> 0 | P8: 1 | Q8: проект | R8: 1 | V8: =(P8*R8*S8)+(T8*U8*P8*R8) -> 0 | W8: 0.09 | X8: =V8/(1-W8) -> 0 | Y8: 0 | Z8: 0.09 | AA8: =Y8/(1-Z8) -> 0
B9: Креативный супервайзинг проекта | E9: 1 | F9: проект | G9: 1 | K9: =(E9*G9*H9)+(I9*J9*E9*G9) -> 0 | L9: 0.09 | M9: =K9/(1-L9) -> 0 | P9: 1 | Q9: проект | R9: 1 | V9: =(P9*R9*S9)+(T9*U9*P9*R9) -> 0 | W9: 0.09 | X9: =V9/(1-W9) -> 0 | Y9: 0 | Z9: 0.09 | AA9: =Y9/(1-Z9) -> 0
B10: Директор рисёрч | E10: 1 | F10: проект | G10: 1 | K10: =(E10*G10*H10)+(I10*J10*E10*G10) -> 0 | L10: 0.09 | M10: =K10/(1-L10) -> 0 | P10: 1 | Q10: проект | R10: 1 | V10: =(P10*R10*S10)+(T10*U10*P10*R10) -> 0 | W10: 0.09 | X10: =V10/(1-W10) -> 0 | Y10: 0 | Z10: 0.09 | AA10: =Y10/(1-Z10) -> 0
B11: Оформление тритмента | E11: 1 | F11: проект | G11: 1 | K11: =(E11*G11*H11)+(I11*J11*E11*G11) -> 0 | L11: 0.09 | M11: =K11/(1-L11) -> 0 | P11: 1 | Q11: проект | R11: 1 | V11: =(P11*R11*S11)+(T11*U11*P11*R11) -> 0 | W11: 0.09 | X11: =V11/(1-W11) -> 0 | Y11: 0 | Z11: 0.09 | AA11: =Y11/(1-Z11) -> 0
B12: Раскадровка | E12: 1 | F12: кадр | G12: 1 | K12: =(E12*G12*H12)+(I12*J12*E12*G12) -> 0 | L12: 0.09 | M12: =K12/(1-L12) -> 0 | P12: 1 | Q12: кадр | R12: 1 | V12: =(P12*R12*S12)+(T12*U12*P12*R12) -> 0 | W12: 0.09 | X12: =V12/(1-W12) -> 0 | Y12: 0 | Z12: 0.09 | AA12: =Y12/(1-Z12) -> 0
B13: Аниматик | E13: 1 | F13: проект | G13: 1 | K13: =(E13*G13*H13)+(I13*J13*E13*G13) -> 0 | L13: 0.09 | M13: =K13/(1-L13) -> 0 | P13: 1 | Q13: проект | R13: 1 | V13: =(P13*R13*S13)+(T13*U13*P13*R13) -> 0 | W13: 0.09 | X13: =V13/(1-W13) -> 0 | Y13: 0 | Z13: 0.09 | AA13: =Y13/(1-Z13) -> 0
B14: ППМ-буклеты | E14: 1 | F14: проект | G14: 1 | K14: =(E14*G14*H14)+(I14*J14*E14*G14) -> 0 | L14: 0.09 | M14: =K14/(1-L14) -> 0 | P14: 1 | Q14: проект | R14: 1 | V14: =(P14*R14*S14)+(T14*U14*P14*R14) -> 0 | W14: 0.09 | X14: =V14/(1-W14) -> 0 | Y14: 0 | Z14: 0.09 | AA14: =Y14/(1-Z14) -> 0
B15: Переводчик | E15: 1 | F15: проект | G15: 1 | K15: =(E15*G15*H15)+(I15*J15*E15*G15) -> 0 | L15: 0.09 | M15: =K15/(1-L15) -> 0 | P15: 1 | Q15: проект | R15: 1 | V15: =(P15*R15*S15)+(T15*U15*P15*R15) -> 0 | W15: 0.09 | X15: =V15/(1-W15) -> 0 | Y15: 0 | Z15: 0.09 | AA15: =Y15/(1-Z15) -> 0
B16: Юридическое сопровождение | E16: 1 | F16: проект | G16: 1 | K16: =(E16*G16*H16)+(I16*J16*E16*G16) -> 0 | L16: 0.09 | M16: =K16/(1-L16) -> 0 | P16: 1 | Q16: проект | R16: 1 | V16: =(P16*R16*S16)+(T16*U16*P16*R16) -> 0 | W16: 0.09 | X16: =V16/(1-W16) -> 0 | Y16: 0 | Z16: 0.09 | AA16: =Y16/(1-Z16) -> 0
B17: Курьер, почтовые расходы | E17: 1 | F17: проект | G17: 1 | K17: =(E17*G17*H17)+(I17*J17*E17*G17) -> 0 | L17: 0.09 | M17: =K17/(1-L17) -> 0 | P17: 1 | Q17: проект | R17: 1 | V17: =(P17*R17*S17)+(T17*U17*P17*R17) -> 0 | W17: 0.09 | X17: =V17/(1-W17) -> 0 | Y17: 0 | Z17: 0.09 | AA17: =Y17/(1-Z17) -> 0
L18: ИТОГО РАЗРАБОТКА | M18: =SUM(M8:M17) -> 0 | W18: ИТОГО РАЗРАБОТКА | X18: =SUM(X8:X17) -> 0 | Z18: ИТОГО РАЗРАБОТКА | AA18: =SUM(AA8:AA17) -> 0
A19: D. ГОНОРАРЫ
B20: РЕЖИССЕРСКИЙ ДЕПАРТАМЕНТ
B21: Режиссер | E21: 1 | F21: проект | G21: 1 | K21: =(E21*G21*H21)+(I21*J21*E21*G21) -> 0 | L21: 0.09 | M21: =K21/(1-L21) -> 0 | P21: 1 | Q21: проект | R21: 1 | V21: =(P21*R21*S21)+(T21*U21*P21*R21) -> 0 | W21: 0.09 | X21: =V21/(1-W21) -> 0 | Y21: 0 | Z21: 0.09 | AA21: =Y21/(1-Z21) -> 0
B22: Второй режиссер | E22: 1 | F22: проект | G22: 1 | K22: =(E22*G22*H22)+(I22*J22*E22*G22) -> 0 | L22: 0.09 | M22: =K22/(1-L22) -> 0 | P22: 1 | Q22: проект | R22: 1 | V22: =(P22*R22*S22)+(T22*U22*P22*R22) -> 0 | W22: 0.09 | X22: =V22/(1-W22) -> 0 | Y22: 0 | Z22: 0.09 | AA22: =Y22/(1-Z22) -> 0
A23: K. ПОСТ-ПРОИЗВОДСТВО
B24: Пост-продакшн продюсер | E24: 1 | F24: проект | G24: 1 | L24: 0.09 | M24: =K24/(1-L24) -> 0 | P24: 1 | Q24: проект | R24: 1 | V24: =(P24*R24*S24)+(T24*U24*P24*R24) -> 0 | W24: 0.09 | X24: =V24/(1-W24) -> 0 | Y24: 0 | Z24: 0.09 | AA24: =Y24/(1-Z24) -> 0
B25: Арт-директор | E25: 1 | F25: проект | G25: 1 | L25: 0.09 | M25: =K25/(1-L25) -> 0 | P25: 1 | Q25: проект | R25: 1 | V25: =(P25*R25*S25)+(T25*U25*P25*R25) -> 0 | W25: 0.09 | X25: =V25/(1-W25) -> 0 | Y25: 0 | Z25: 0.09 | AA25: =Y25/(1-Z25) -> 0
B26: МОНТАЖ И ЦВЕТОКОРРЕКЦИЯ
B27: Режиссер монтажа | E27: 1 | F27: час | G27: 1 | K27: =(E27*G27*H27)+(I27*J27*E27*G27) -> 0 | L27: 0.09 | M27: =K27/(1-L27) -> 0 | P27: 1 | Q27: час | R27: 1 | V27: =(P27*R27*S27)+(T27*U27*P27*R27) -> 0 | W27: 0.09 | X27: =V27/(1-W27) -> 0 | Y27: 0 | Z27: 0.09 | AA27: =Y27/(1-Z27) -> 0
B28: Технический монтаж | E28: 1 | F28: час | G28: 1 | K28: =(E28*G28*H28)+(I28*J28*E28*G28) -> 0 | L28: 0.09 | M28: =K28/(1-L28) -> 0 | P28: 1 | Q28: час | R28: 1 | V28: =(P28*R28*S28)+(T28*U28*P28*R28) -> 0 | W28: 0.09 | X28: =V28/(1-W28) -> 0 | Y28: 0 | Z28: 0.09 | AA28: =Y28/(1-Z28) -> 0
B29: Цветокоррекция | E29: 1 | F29: час | G29: 1 | K29: =(E29*G29*H29)+(I29*J29*E29*G29) -> 0 | L29: 0.09 | M29: =K29/(1-L29) -> 0 | P29: 1 | Q29: час | R29: 1 | V29: =(P29*R29*S29)+(T29*U29*P29*R29) -> 0 | W29: 0.09 | X29: =V29/(1-W29) -> 0 | Y29: 0 | Z29: 0.09 | AA29: =Y29/(1-Z29) -> 0
B30: КОМПЬЮТЕРНАЯ ГРАФИКА
B31: Стоковые материалы | E31: 1 | F31: шт | G31: 1 | K31: =(E31*G31*H31)+(I31*J31*E31*G31) -> 0 | L31: 0.09 | M31: =K31/(1-L31) -> 0 | P31: 1 | Q31: шт | R31: 1 | V31: =(P31*R31*S31)+(T31*U31*P31*R31) -> 0 | W31: 0.09 | X31: =V31/(1-W31) -> 0 | Y31: 0 | Z31: 0.09 | AA31: =Y31/(1-Z31) -> 0
B32: VFX супервайзер | E32: 1 | F32: смена | G32: 1 | K32: =(E32*G32*H32)+(I32*J32*E32*G32) -> 0 | L32: 0.09 | M32: =K32/(1-L32) -> 0 | P32: 1 | Q32: смена | R32: 1 | V32: =(P32*R32*S32)+(T32*U32*P32*R32) -> 0 | W32: 0.09 | X32: =V32/(1-W32) -> 0 | Y32: 0 | Z32: 0.09 | AA32: =Y32/(1-Z32) -> 0
B33: Иллюстратор | E33: 1 | F33: проект | G33: 1 | K33: =(E33*G33*H33)+(I33*J33*E33*G33) -> 0 | L33: 0.09 | M33: =K33/(1-L33) -> 0 | P33: 1 | Q33: проект | R33: 1 | V33: =(P33*R33*S33)+(T33*U33*P33*R33) -> 0 | W33: 0.09 | X33: =V33/(1-W33) -> 0 | Y33: 0 | Z33: 0.09 | AA33: =Y33/(1-Z33) -> 0
B34: 2D анимация | E34: 1 | F34: проект | G34: 1 | K34: =(E34*G34*H34)+(I34*J34*E34*G34) -> 0 | L34: 0.09 | M34: =K34/(1-L34) -> 0 | P34: 1 | Q34: проект | R34: 1 | V34: =(P34*R34*S34)+(T34*U34*P34*R34) -> 0 | W34: 0.09 | X34: =V34/(1-W34) -> 0 | Y34: 0 | Z34: 0.09 | AA34: =Y34/(1-Z34) -> 0
B35: 3D анимация | E35: 1 | F35: проект | G35: 1 | K35: =(E35*G35*H35)+(I35*J35*E35*G35) -> 0 | L35: 0.09 | M35: =K35/(1-L35) -> 0 | P35: 1 | Q35: проект | R35: 1 | V35: =(P35*R35*S35)+(T35*U35*P35*R35) -> 0 | W35: 0.09 | X35: =V35/(1-W35) -> 0 | Y35: 0 | Z35: 0.09 | AA35: =Y35/(1-Z35) -> 0
B36: Моделинг | E36: 1 | F36: проект | G36: 1 | K36: =(E36*G36*H36)+(I36*J36*E36*G36) -> 0 | L36: 0.09 | M36: =K36/(1-L36) -> 0 | P36: 1 | Q36: проект | R36: 1 | V36: =(P36*R36*S36)+(T36*U36*P36*R36) -> 0 | W36: 0.09 | X36: =V36/(1-W36) -> 0 | Y36: 0 | Z36: 0.09 | AA36: =Y36/(1-Z36) -> 0
B37: Лайтнинг | E37: 1 | F37: проект | G37: 1 | K37: =(E37*G37*H37)+(I37*J37*E37*G37) -> 0 | L37: 0.09 | M37: =K37/(1-L37) -> 0 | P37: 1 | Q37: проект | R37: 1 | V37: =(P37*R37*S37)+(T37*U37*P37*R37) -> 0 | W37: 0.09 | X37: =V37/(1-W37) -> 0 | Y37: 0 | Z37: 0.09 | AA37: =Y37/(1-Z37) -> 0
B38: Шейдинг | E38: 1 | F38: проект | G38: 1 | K38: =(E38*G38*H38)+(I38*J38*E38*G38) -> 0 | L38: 0.09 | M38: =K38/(1-L38) -> 0 | P38: 1 | Q38: проект | R38: 1 | V38: =(P38*R38*S38)+(T38*U38*P38*R38) -> 0 | W38: 0.09 | X38: =V38/(1-W38) -> 0 | Y38: 0 | Z38: 0.09 | AA38: =Y38/(1-Z38) -> 0
B39: Трекинг | E39: 1 | F39: проект | G39: 1 | K39: =(E39*G39*H39)+(I39*J39*E39*G39) -> 0 | L39: 0.09 | M39: =K39/(1-L39) -> 0 | P39: 1 | Q39: проект | R39: 1 | V39: =(P39*R39*S39)+(T39*U39*P39*R39) -> 0 | W39: 0.09 | X39: =V39/(1-W39) -> 0 | Y39: 0 | Z39: 0.09 | AA39: =Y39/(1-Z39) -> 0
B40: Композитинг | E40: 1 | F40: проект | G40: 1 | K40: =(E40*G40*H40)+(I40*J40*E40*G40) -> 0 | L40: 0.09 | M40: =K40/(1-L40) -> 0 | P40: 1 | Q40: проект | R40: 1 | V40: =(P40*R40*S40)+(T40*U40*P40*R40) -> 0 | W40: 0.09 | X40: =V40/(1-W40) -> 0 | Y40: 0 | Z40: 0.09 | AA40: =Y40/(1-Z40) -> 0
B41: Клинап | E41: 1 | F41: проект | G41: 1 | K41: =(E41*G41*H41)+(I41*J41*E41*G41) -> 0 | L41: 0.09 | M41: =K41/(1-L41) -> 0 | P41: 1 | Q41: проект | R41: 1 | V41: =(P41*R41*S41)+(T41*U41*P41*R41) -> 0 | W41: 0.09 | X41: =V41/(1-W41) -> 0 | Y41: 0 | Z41: 0.09 | AA41: =Y41/(1-Z41) -> 0
B42: Рендер | E42: 1 | F42: проект | G42: 1 | K42: =(E42*G42*H42)+(I42*J42*E42*G42) -> 0 | L42: 0.09 | M42: =K42/(1-L42) -> 0 | P42: 1 | Q42: проект | R42: 1 | V42: =(P42*R42*S42)+(T42*U42*P42*R42) -> 0 | W42: 0.09 | X42: =V42/(1-W42) -> 0 | Z42: 0.09 | AA42: =Y42/(1-Z42) -> 0
B43: ИИ ГРАФИКА
B44: ИИ продюсер | E44: 1 | F44: шт | G44: 1 | K44: =(E44*G44*H44)+(I44*J44*E44*G44) -> 0 | L44: 0.09 | M44: =K44/(1-L44) -> 0 | P44: 1 | Q44: шт | R44: 1 | V44: =(P44*R44*S44)+(T44*U44*P44*R44) -> 0 | W44: 0.09 | X44: =V44/(1-W44) -> 0 | Y44: 0 | Z44: 0.09 | AA44: =Y44/(1-Z44) -> 0
B45: ИИ aрт-директор | E45: 1 | F45: шт | G45: 1 | K45: =(E45*G45*H45)+(I45*J45*E45*G45) -> 0 | L45: 0.09 | M45: =K45/(1-L45) -> 0 | P45: 1 | Q45: шт | R45: 1 | V45: =(P45*R45*S45)+(T45*U45*P45*R45) -> 0 | W45: 0.09 | X45: =V45/(1-W45) -> 0 | Y45: 0 | Z45: 0.09 | AA45: =Y45/(1-Z45) -> 0
B46: ИИ супервайзер | E46: 1 | F46: шт | G46: 1 | K46: =(E46*G46*H46)+(I46*J46*E46*G46) -> 0 | L46: 0.09 | M46: =K46/(1-L46) -> 0 | P46: 1 | Q46: шт | R46: 1 | V46: =(P46*R46*S46)+(T46*U46*P46*R46) -> 0 | W46: 0.09 | X46: =V46/(1-W46) -> 0 | Y46: 0 | Z46: 0.09 | AA46: =Y46/(1-Z46) -> 0
B47: Аниматик | E47: 1 | F47: шт | G47: 1 | K47: =(E47*G47*H47)+(I47*J47*E47*G47) -> 0 | L47: 0.09 | M47: =K47/(1-L47) -> 0 | P47: 1 | Q47: шт | R47: 1 | V47: =(P47*R47*S47)+(T47*U47*P47*R47) -> 0 | W47: 0.09 | X47: =V47/(1-W47) -> 0 | Y47: 0 | Z47: 0.09 | AA47: =Y47/(1-Z47) -> 0
B48: Фото генерации | E48: 1 | F48: шт | G48: 1 | K48: =(E48*G48*H48)+(I48*J48*E48*G48) -> 0 | L48: 0.09 | M48: =K48/(1-L48) -> 0 | P48: 1 | Q48: шт | R48: 1 | V48: =(P48*R48*S48)+(T48*U48*P48*R48) -> 0 | W48: 0.09 | X48: =V48/(1-W48) -> 0 | Y48: 0 | Z48: 0.09 | AA48: =Y48/(1-Z48) -> 0
B49: Инпейнт (детальная доработка) | E49: 1 | F49: шт | G49: 1 | K49: =(E49*G49*H49)+(I49*J49*E49*G49) -> 0 | L49: 0.09 | M49: =K49/(1-L49) -> 0 | P49: 1 | Q49: шт | R49: 1 | V49: =(P49*R49*S49)+(T49*U49*P49*R49) -> 0 | W49: 0.09 | X49: =V49/(1-W49) -> 0 | Y49: 0 | Z49: 0.09 | AA49: =Y49/(1-Z49) -> 0
B50: Видео генерации | E50: 1 | F50: шт | G50: 1 | K50: =(E50*G50*H50)+(I50*J50*E50*G50) -> 0 | L50: 0.09 | M50: =K50/(1-L50) -> 0 | P50: 1 | Q50: шт | R50: 1 | V50: =(P50*R50*S50)+(T50*U50*P50*R50) -> 0 | W50: 0.09 | X50: =V50/(1-W50) -> 0 | Y50: 0 | Z50: 0.09 | AA50: =Y50/(1-Z50) -> 0
B51: Клинап | E51: 1 | F51: шт | G51: 1 | K51: =(E51*G51*H51)+(I51*J51*E51*G51) -> 0 | L51: 0.09 | M51: =K51/(1-L51) -> 0 | P51: 1 | Q51: шт | R51: 1 | V51: =(P51*R51*S51)+(T51*U51*P51*R51) -> 0 | W51: 0.09 | X51: =V51/(1-W51) -> 0 | Y51: 0 | Z51: 0.09 | AA51: =Y51/(1-Z51) -> 0
B52: Оплата лицензионных сервисов | E52: 1 | F52: шт | G52: 1 | K52: =(E52*G52*H52)+(I52*J52*E52*G52) -> 0 | L52: 0.09 | M52: =K52/(1-L52) -> 0 | P52: 1 | Q52: шт | R52: 1 | V52: =(P52*R52*S52)+(T52*U52*P52*R52) -> 0 | W52: 0.09 | X52: =V52/(1-W52) -> 0 | Y52: 0 | Z52: 0.09 | AA52: =Y52/(1-Z52) -> 0
B53: ЗВУК
B54: Стоковая музыка | E54: 1 | F54: шт | G54: 1 | K54: =(E54*G54*H54)+(I54*J54*E54*G54) -> 0 | L54: 0.09 | M54: =K54/(1-L54) -> 0 | P54: 1 | Q54: шт | R54: 1 | V54: =(P54*R54*S54)+(T54*U54*P54*R54) -> 0 | W54: 0.09 | X54: =V54/(1-W54) -> 0 | Y54: 0 | Z54: 0.09 | AA54: =Y54/(1-Z54) -> 0
B55: Композитор | E55: 1 | F55: проект | G55: 1 | K55: =(E55*G55*H55)+(I55*J55*E55*G55) -> 0 | L55: 0.09 | M55: =K55/(1-L55) -> 0 | P55: 1 | Q55: проект | R55: 1 | V55: =(P55*R55*S55)+(T55*U55*P55*R55) -> 0 | W55: 0.09 | X55: =V55/(1-W55) -> 0 | Y55: 0 | Z55: 0.09 | AA55: =Y55/(1-Z55) -> 0
B56: Диктор | E56: 1 | F56: проект | G56: 1 | K56: =(E56*G56*H56)+(I56*J56*E56*G56) -> 0 | L56: 0.09 | M56: =K56/(1-L56) -> 0 | P56: 1 | Q56: проект | R56: 1 | V56: =(P56*R56*S56)+(T56*U56*P56*R56) -> 0 | W56: 0.09 | X56: =V56/(1-W56) -> 0 | Y56: 0 | Z56: 0.09 | AA56: =Y56/(1-Z56) -> 0
B57: Студия звукозаписи | E57: 1 | F57: час | G57: 1 | K57: =(E57*G57*H57)+(I57*J57*E57*G57) -> 0 | L57: 0.09 | M57: =K57/(1-L57) -> 0 | P57: 1 | Q57: час | R57: 1 | V57: =(P57*R57*S57)+(T57*U57*P57*R57) -> 0 | W57: 0.09 | X57: =V57/(1-W57) -> 0 | Y57: 0 | Z57: 0.09 | AA57: =Y57/(1-Z57) -> 0
B58: Саунд-дизайн и сведение звука | E58: 1 | F58: ролик | G58: 1 | K58: =(E58*G58*H58)+(I58*J58*E58*G58) -> 0 | L58: 0.09 | M58: =K58/(1-L58) -> 0 | P58: 1 | Q58: ролик | R58: 1 | V58: =(P58*R58*S58)+(T58*U58*P58*R58) -> 0 | W58: 0.09 | X58: =V58/(1-W58) -> 0 | Y58: 0 | Z58: 0.09 | AA58: =Y58/(1-Z58) -> 0
L59: ИТОГО ПОСТ-ПРОИЗВОДСТВО | M59: =SUM(M24:M58) -> 0 | W59: ИТОГО ПОСТ-ПРОИЗВОДСТВО | X59: =SUM(X24:X58) -> 0 | Z59: ИТОГО ПОСТ-ПРОИЗВОДСТВО | AA59: =SUM(AA24:AA58) -> 0
L61: ПРОИЗВОДСТВО | M61: =M18+M21+M22 -> 0 | W61: ПРОИЗВОДСТВО | X61: =X18+X21+X22 -> 0 | Z61: ПРОИЗВОДСТВО | AA61: =AA18+AA21+AA22 -> 0
L62: ПОСТ-ПРОИЗВОДСТВО | M62: =M59 -> 0 | W62: ПОСТ-ПРОИЗВОДСТВО | X62: =X59 -> 0 | Z62: ПОСТ-ПРОИЗВОДСТВО | AA62: =AA59 -> 0
K63: НЕПРЕДВИДЕННЫЕ РАСХОДЫ | L63: 0 | M63: =(M61+M62)*L63 -> 0 | W63: НЕПРЕДВИДЕННЫЕ РАСХОДЫ | X63: =M63 -> 0 | Z63: НЕПРЕДВИДЕННЫЕ РАСХОДЫ | AA63: 0
L64: ИТОГО ПРОИЗВОДСТВО | M64: =M61+M62+M63 -> 0 | W64: ИТОГО ПРОИЗВОДСТВО | X64: =X61+X62+X63 -> 0 | Z64: ИТОГО БЕЗ КРЕДИТОВАНИЯ | AA64: =AA61+AA62+AA63 -> 0
K65: МАРКАП | L65: 0.1 | M65: =M64*L65 -> 0
K66: КРЕДИТ, МЕСЯЦЕВ (4,5%) | L66: 0 | M66: =M64*L66*4.5% -> 0 | V66: КРЕДИТ, МЕСЯЦЕВ | W66: =L66 -> 0 | X66: =X64*W66*4.5%/2 -> 0 | Z66: КРЕДИТ, МЕСЯЦЕВ | AA66: =X66 -> 0
L67: ИТОГО ДО НДС | M67: =SUM(M64+M65+M66) -> 0 | W67: ИТОГО РАСХОДОВ ПО ПРОЕКТУ | X67: =SUM(X64+X66) -> 0 | Z67: ИТОГО РАСХОДОВ ПО ПРОЕКТУ | AA67: =SUM(AA64+AA66) -> 0
L68: НДС, 22% | M68: =M67*0.22 -> 0
L69: ИТОГО С НДС | M69: =M67+M68 -> 0
B71: Примечания: | E71: - Смета актуальна для условий, указанных в продакшн подходе, а именно: права, даты съемок, даты запуска (подтверждения), даты сдача мастеров, творческой группы. В случае изменения любых условий смета может быть пересчитана. - При отмене, переносе или остановке проекта по вашей инициативе, вы берете на себя обязательства компенсировать все понесенные исполнителем расходы, а также обязательства перед подрядчиками исполнителя, возникшие на момент отмены, переноса или остановки проекта. - Если договор не будет подписан до съемочного дня, мы оставляем за собой право приостановить проект, при этом вы должны будете компенсировать все понесенные нами расходы, а также обязательства перед нашими подрядчиками, возникшие на тот момент. - В смете не учтены расходы на “погодный день”. | P71: ПРИБЫЛЬ (ПЛАН) | X71: =M67-X67 -> 0 | Y71: ПРИБЫЛЬ (ФАКТ) | AA71: =M67-AA67 -> 0
X72: =X71/M67 -> #DIV/0! | AA72: =AA71/M67 -> #DIV/0!

Sheet CE (ИП)
K1: ИТОГО, ВКЛЮЧАЯ УСН И НДС | M1: =M69 -> 0 | O1: IN COST | P1: ЦЕЛЬ | R1: 0.2 | S1: МАРЖ–ТЬ (ПЛАН) | T1: =X72 -> #DIV/0! | U1: IN-COST (ПЛАН) | V1: =X64 -> 0 | X1: МАРЖ-ТЬ (ФАКТ) | Y1: =AA72 -> #DIV/0! | Z1: IN-COST (ФАКТ) | AA1: =AA67 -> 0
C2: Название проекта | E2: кол-во | F2: наименование единицы | G2: единица | H2: цена за единицу | I2: переработки (всего) | K2: подытог | L2: налоговая ставка | M2: итого c налогами | N2: комментарии | P2: кол-во | Q2: наименование единицы | R2: единица | S2: цена за единицу | T2: переработки (всего) | V2: подытог (ПЛАН) | W2: Налоговая ставка | X2: Итого c налогами (ПЛАН) | Y2: подытог (ФАКТ) | Z2: налог | AA2: Итого c налогами (ФАКТ)
I4: часы | J4: ставка | T4: часы | U4: ставка
A7: A. РАЗРАБОТКА
B8: Разработка креатива | E8: 1 | F8: проект | G8: 1 | K8: =(E8*G8*H8)+(I8*J8*E8*G8) -> 0 | L8: 0.09 | M8: =K8/(1-L8) -> 0 | P8: 1 | Q8: проект | R8: 1 | V8: =(P8*R8*S8)+(T8*U8*P8*R8) -> 0 | W8: 0.09 | X8: =V8/(1-W8) -> 0 | Y8: 0 | Z8: 0.09 | AA8: =Y8/(1-Z8) -> 0
B9: Креативный супервайзинг проекта | E9: 1 | F9: проект | G9: 1 | K9: =(E9*G9*H9)+(I9*J9*E9*G9) -> 0 | L9: 0.09 | M9: =K9/(1-L9) -> 0 | P9: 1 | Q9: проект | R9: 1 | V9: =(P9*R9*S9)+(T9*U9*P9*R9) -> 0 | W9: 0.09 | X9: =V9/(1-W9) -> 0 | Y9: 0 | Z9: 0.09 | AA9: =Y9/(1-Z9) -> 0
B10: Директор рисёрч | E10: 1 | F10: проект | G10: 1 | K10: =(E10*G10*H10)+(I10*J10*E10*G10) -> 0 | L10: 0.09 | M10: =K10/(1-L10) -> 0 | P10: 1 | Q10: проект | R10: 1 | V10: =(P10*R10*S10)+(T10*U10*P10*R10) -> 0 | W10: 0.09 | X10: =V10/(1-W10) -> 0 | Y10: 0 | Z10: 0.09 | AA10: =Y10/(1-Z10) -> 0
B11: Сценарий | E11: 1 | F11: проект | G11: 1 | K11: =(E11*G11*H11)+(I11*J11*E11*G11) -> 0 | L11: 0.09 | M11: =K11/(1-L11) -> 0 | P11: 1 | Q11: проект | R11: 1 | V11: =(P11*R11*S11)+(T11*U11*P11*R11) -> 0 | W11: 0.09 | X11: =V11/(1-W11) -> 0 | Y11: 0 | Z11: 0.09 | AA11: =Y11/(1-Z11) -> 0
B12: Раскадровка | E12: 1 | F12: кадр | G12: 1 | K12: =(E12*G12*H12)+(I12*J12*E12*G12) -> 0 | L12: 0.09 | M12: =K12/(1-L12) -> 0 | P12: 1 | Q12: кадр | R12: 1 | V12: =(P12*R12*S12)+(T12*U12*P12*R12) -> 0 | W12: 0.09 | X12: =V12/(1-W12) -> 0 | Y12: 0 | Z12: 0.09 | AA12: =Y12/(1-Z12) -> 0
B13: Аниматик | E13: 1 | F13: проект | G13: 1 | K13: =(E13*G13*H13)+(I13*J13*E13*G13) -> 0 | L13: 0.09 | M13: =K13/(1-L13) -> 0 | P13: 1 | Q13: проект | R13: 1 | V13: =(P13*R13*S13)+(T13*U13*P13*R13) -> 0 | W13: 0.09 | X13: =V13/(1-W13) -> 0 | Y13: 0 | Z13: 0.09 | AA13: =Y13/(1-Z13) -> 0
B14: ППМ-буклеты | E14: 1 | F14: проект | G14: 1 | K14: =(E14*G14*H14)+(I14*J14*E14*G14) -> 0 | L14: 0.09 | M14: =K14/(1-L14) -> 0 | P14: 1 | Q14: проект | R14: 1 | V14: =(P14*R14*S14)+(T14*U14*P14*R14) -> 0 | W14: 0.09 | X14: =V14/(1-W14) -> 0 | Y14: 0 | Z14: 0.09 | AA14: =Y14/(1-Z14) -> 0
B15: Переводчик | E15: 1 | F15: проект | G15: 1 | K15: =(E15*G15*H15)+(I15*J15*E15*G15) -> 0 | L15: 0.09 | M15: =K15/(1-L15) -> 0 | P15: 1 | Q15: проект | R15: 1 | V15: =(P15*R15*S15)+(T15*U15*P15*R15) -> 0 | W15: 0.09 | X15: =V15/(1-W15) -> 0 | Y15: 0 | Z15: 0.09 | AA15: =Y15/(1-Z15) -> 0
B16: Юридическое сопровождение | E16: 1 | F16: проект | G16: 1 | K16: =(E16*G16*H16)+(I16*J16*E16*G16) -> 0 | L16: 0.09 | M16: =K16/(1-L16) -> 0 | P16: 1 | Q16: проект | R16: 1 | V16: =(P16*R16*S16)+(T16*U16*P16*R16) -> 0 | W16: 0.09 | X16: =V16/(1-W16) -> 0 | Y16: 0 | Z16: 0.09 | AA16: =Y16/(1-Z16) -> 0
B17: Курьер, почтовые расходы | E17: 1 | F17: проект | G17: 1 | K17: =(E17*G17*H17)+(I17*J17*E17*G17) -> 0 | L17: 0.09 | M17: =K17/(1-L17) -> 0 | P17: 1 | Q17: проект | R17: 1 | V17: =(P17*R17*S17)+(T17*U17*P17*R17) -> 0 | W17: 0.09 | X17: =V17/(1-W17) -> 0 | Y17: 0 | Z17: 0.09 | AA17: =Y17/(1-Z17) -> 0
L18: ИТОГО РАЗРАБОТКА | M18: =SUM(M8:M17) -> 0 | W18: ИТОГО РАЗРАБОТКА | X18: =SUM(X8:X17) -> 0 | Z18: ИТОГО РАЗРАБОТКА | AA18: =SUM(AA8:AA17) -> 0
A19: D. ГОНОРАРЫ
B20: РЕЖИССЕРСКИЙ ДЕПАРТАМЕНТ
B21: Режиссер | E21: 1 | F21: проект | G21: 1 | K21: =(E21*G21*H21)+(I21*J21*E21*G21) -> 0 | L21: 0.09 | M21: =K21/(1-L21) -> 0 | P21: 1 | Q21: проект | R21: 1 | V21: =(P21*R21*S21)+(T21*U21*P21*R21) -> 0 | W21: 0.09 | X21: =V21/(1-W21) -> 0 | Y21: 0 | Z21: 0.09 | AA21: =Y21/(1-Z21) -> 0
B22: Второй режиссер | E22: 1 | F22: проект | G22: 1 | K22: =(E22*G22*H22)+(I22*J22*E22*G22) -> 0 | L22: 0.09 | M22: =K22/(1-L22) -> 0 | P22: 1 | Q22: проект | R22: 1 | V22: =(P22*R22*S22)+(T22*U22*P22*R22) -> 0 | W22: 0.09 | X22: =V22/(1-W22) -> 0 | Y22: 0 | Z22: 0.09 | AA22: =Y22/(1-Z22) -> 0
A23: K. ПОСТ-ПРОИЗВОДСТВО
B24: Пост-продакшн продюсер | E24: 1 | F24: проект | G24: 1 | K24: =(E24*G24*H24)+(I24*J24*E24*G24) -> 0 | L24: 0.09 | M24: =K24/(1-L24) -> 0 | P24: 1 | Q24: проект | R24: 1 | V24: =(P24*R24*S24)+(T24*U24*P24*R24) -> 0 | W24: 0.09 | X24: =V24/(1-W24) -> 0 | Y24: 0 | Z24: 0.09 | AA24: =Y24/(1-Z24) -> 0
B25: Арт-директор | E25: 1 | F25: проект | G25: 1 | K25: =(E25*G25*H25)+(I25*J25*E25*G25) -> 0 | L25: 0.09 | M25: =K25/(1-L25) -> 0 | P25: 1 | Q25: проект | R25: 1 | V25: =(P25*R25*S25)+(T25*U25*P25*R25) -> 0 | W25: 0.09 | X25: =V25/(1-W25) -> 0 | Y25: 0 | Z25: 0.09 | AA25: =Y25/(1-Z25) -> 0
B26: МОНТАЖ И ЦВЕТОКОРРЕКЦИЯ
B27: Режиссер монтажа | E27: 1 | F27: час | G27: 1 | K27: =(E27*G27*H27)+(I27*J27*E27*G27) -> 0 | L27: 0.09 | M27: =K27/(1-L27) -> 0 | P27: 1 | Q27: час | R27: 1 | V27: =(P27*R27*S27)+(T27*U27*P27*R27) -> 0 | W27: 0.09 | X27: =V27/(1-W27) -> 0 | Y27: 0 | Z27: 0.09 | AA27: =Y27/(1-Z27) -> 0
B28: Технический монтаж | E28: 1 | F28: час | G28: 1 | K28: =(E28*G28*H28)+(I28*J28*E28*G28) -> 0 | L28: 0.09 | M28: =K28/(1-L28) -> 0 | P28: 1 | Q28: час | R28: 1 | V28: =(P28*R28*S28)+(T28*U28*P28*R28) -> 0 | W28: 0.09 | X28: =V28/(1-W28) -> 0 | Y28: 0 | Z28: 0.09 | AA28: =Y28/(1-Z28) -> 0
B29: Цветокоррекция | E29: 1 | F29: час | G29: 1 | K29: =(E29*G29*H29)+(I29*J29*E29*G29) -> 0 | L29: 0.09 | M29: =K29/(1-L29) -> 0 | P29: 1 | Q29: час | R29: 1 | V29: =(P29*R29*S29)+(T29*U29*P29*R29) -> 0 | W29: 0.09 | X29: =V29/(1-W29) -> 0 | Y29: 0 | Z29: 0.09 | AA29: =Y29/(1-Z29) -> 0
B30: КОМПЬЮТЕРНАЯ ГРАФИКА
B31: Стоковые материалы | E31: 1 | F31: шт | G31: 1 | K31: =(E31*G31*H31)+(I31*J31*E31*G31) -> 0 | L31: 0.09 | M31: =K31/(1-L31) -> 0 | P31: 1 | Q31: шт | R31: 1 | V31: =(P31*R31*S31)+(T31*U31*P31*R31) -> 0 | W31: 0.09 | X31: =V31/(1-W31) -> 0 | Y31: 0 | Z31: 0.09 | AA31: =Y31/(1-Z31) -> 0
B32: VFX супервайзер | E32: 1 | F32: смена | G32: 1 | K32: =(E32*G32*H32)+(I32*J32*E32*G32) -> 0 | L32: 0.09 | M32: =K32/(1-L32) -> 0 | P32: 1 | Q32: смена | R32: 1 | V32: =(P32*R32*S32)+(T32*U32*P32*R32) -> 0 | W32: 0.09 | X32: =V32/(1-W32) -> 0 | Y32: 0 | Z32: 0.09 | AA32: =Y32/(1-Z32) -> 0
B33: Иллюстратор | E33: 1 | F33: проект | G33: 1 | K33: =(E33*G33*H33)+(I33*J33*E33*G33) -> 0 | L33: 0.09 | M33: =K33/(1-L33) -> 0 | P33: 1 | Q33: проект | R33: 1 | V33: =(P33*R33*S33)+(T33*U33*P33*R33) -> 0 | W33: 0.09 | X33: =V33/(1-W33) -> 0 | Y33: 0 | Z33: 0.09 | AA33: =Y33/(1-Z33) -> 0
B34: 2D анимация | E34: 1 | F34: проект | G34: 1 | K34: =(E34*G34*H34)+(I34*J34*E34*G34) -> 0 | L34: 0.09 | M34: =K34/(1-L34) -> 0 | P34: 1 | Q34: проект | R34: 1 | V34: =(P34*R34*S34)+(T34*U34*P34*R34) -> 0 | W34: 0.09 | X34: =V34/(1-W34) -> 0 | Y34: 0 | Z34: 0.09 | AA34: =Y34/(1-Z34) -> 0
B35: 3D анимация | E35: 1 | F35: проект | G35: 1 | K35: =(E35*G35*H35)+(I35*J35*E35*G35) -> 0 | L35: 0.09 | M35: =K35/(1-L35) -> 0 | P35: 1 | Q35: проект | R35: 1 | V35: =(P35*R35*S35)+(T35*U35*P35*R35) -> 0 | W35: 0.09 | X35: =V35/(1-W35) -> 0 | Y35: 0 | Z35: 0.09 | AA35: =Y35/(1-Z35) -> 0
B36: Моделинг | E36: 1 | F36: проект | G36: 1 | K36: =(E36*G36*H36)+(I36*J36*E36*G36) -> 0 | L36: 0.09 | M36: =K36/(1-L36) -> 0 | P36: 1 | Q36: проект | R36: 1 | V36: =(P36*R36*S36)+(T36*U36*P36*R36) -> 0 | W36: 0.09 | X36: =V36/(1-W36) -> 0 | Y36: 0 | Z36: 0.09 | AA36: =Y36/(1-Z36) -> 0
B37: Лайтнинг | E37: 1 | F37: проект | G37: 1 | K37: =(E37*G37*H37)+(I37*J37*E37*G37) -> 0 | L37: 0.09 | M37: =K37/(1-L37) -> 0 | P37: 1 | Q37: проект | R37: 1 | V37: =(P37*R37*S37)+(T37*U37*P37*R37) -> 0 | W37: 0.09 | X37: =V37/(1-W37) -> 0 | Y37: 0 | Z37: 0.09 | AA37: =Y37/(1-Z37) -> 0
B38: Шейдинг | E38: 1 | F38: проект | G38: 1 | K38: =(E38*G38*H38)+(I38*J38*E38*G38) -> 0 | L38: 0.09 | M38: =K38/(1-L38) -> 0 | P38: 1 | Q38: проект | R38: 1 | V38: =(P38*R38*S38)+(T38*U38*P38*R38) -> 0 | W38: 0.09 | X38: =V38/(1-W38) -> 0 | Y38: 0 | Z38: 0.09 | AA38: =Y38/(1-Z38) -> 0
B39: Трекинг | E39: 1 | F39: проект | G39: 1 | K39: =(E39*G39*H39)+(I39*J39*E39*G39) -> 0 | L39: 0.09 | M39: =K39/(1-L39) -> 0 | P39: 1 | Q39: проект | R39: 1 | V39: =(P39*R39*S39)+(T39*U39*P39*R39) -> 0 | W39: 0.09 | X39: =V39/(1-W39) -> 0 | Y39: 0 | Z39: 0.09 | AA39: =Y39/(1-Z39) -> 0
B40: Композитинг | E40: 1 | F40: проект | G40: 1 | K40: =(E40*G40*H40)+(I40*J40*E40*G40) -> 0 | L40: 0.09 | M40: =K40/(1-L40) -> 0 | P40: 1 | Q40: проект | R40: 1 | V40: =(P40*R40*S40)+(T40*U40*P40*R40) -> 0 | W40: 0.09 | X40: =V40/(1-W40) -> 0 | Y40: 0 | Z40: 0.09 | AA40: =Y40/(1-Z40) -> 0
B41: Клинап | E41: 1 | F41: проект | G41: 1 | K41: =(E41*G41*H41)+(I41*J41*E41*G41) -> 0 | L41: 0.09 | M41: =K41/(1-L41) -> 0 | P41: 1 | Q41: проект | R41: 1 | V41: =(P41*R41*S41)+(T41*U41*P41*R41) -> 0 | W41: 0.09 | X41: =V41/(1-W41) -> 0 | Y41: 0 | Z41: 0.09 | AA41: =Y41/(1-Z41) -> 0
B42: Рендер | E42: 1 | F42: проект | G42: 1 | K42: =(E42*G42*H42)+(I42*J42*E42*G42) -> 0 | L42: 0.09 | M42: =K42/(1-L42) -> 0 | P42: 1 | Q42: проект | R42: 1 | V42: =(P42*R42*S42)+(T42*U42*P42*R42) -> 0 | W42: 0.09 | X42: =V42/(1-W42) -> 0 | Y42: 0 | Z42: 0.09 | AA42: =Y42/(1-Z42) -> 0
B43: ИИ ГРАФИКА
B44: ИИ продюсер | E44: 1 | F44: проект | G44: 1 | K44: =(E44*G44*H44)+(I44*J44*E44*G44) -> 0 | L44: 0.09 | M44: =K44/(1-L44) -> 0 | P44: 1 | Q44: проект | R44: 1 | V44: =(P44*R44*S44)+(T44*U44*P44*R44) -> 0 | W44: 0.09 | X44: =V44/(1-W44) -> 0 | Y44: 0 | Z44: 0.09 | AA44: =Y44/(1-Z44) -> 0
B45: ИИ aрт-директор | E45: 1 | F45: проект | G45: 1 | K45: =(E45*G45*H45)+(I45*J45*E45*G45) -> 0 | L45: 0.09 | M45: =K45/(1-L45) -> 0 | P45: 1 | Q45: проект | R45: 1 | V45: =(P45*R45*S45)+(T45*U45*P45*R45) -> 0 | W45: 0.09 | X45: =V45/(1-W45) -> 0 | Y45: 0 | Z45: 0.09 | AA45: =Y45/(1-Z45) -> 0
B46: ИИ супервайзер | E46: 1 | F46: проект | G46: 1 | K46: =(E46*G46*H46)+(I46*J46*E46*G46) -> 0 | L46: 0.09 | M46: =K46/(1-L46) -> 0 | P46: 1 | Q46: проект | R46: 1 | V46: =(P46*R46*S46)+(T46*U46*P46*R46) -> 0 | W46: 0.09 | X46: =V46/(1-W46) -> 0 | Y46: 0 | Z46: 0.09 | AA46: =Y46/(1-Z46) -> 0
B47: Аниматик | E47: 1 | F47: проект | G47: 1 | K47: =(E47*G47*H47)+(I47*J47*E47*G47) -> 0 | L47: 0.09 | M47: =K47/(1-L47) -> 0 | P47: 1 | Q47: проект | R47: 1 | V47: =(P47*R47*S47)+(T47*U47*P47*R47) -> 0 | W47: 0.09 | X47: =V47/(1-W47) -> 0 | Y47: 0 | Z47: 0.09 | AA47: =Y47/(1-Z47) -> 0
B48: Фото генерации | E48: 1 | F48: проект | G48: 1 | K48: =(E48*G48*H48)+(I48*J48*E48*G48) -> 0 | L48: 0.09 | M48: =K48/(1-L48) -> 0 | P48: 1 | Q48: проект | R48: 1 | V48: =(P48*R48*S48)+(T48*U48*P48*R48) -> 0 | W48: 0.09 | X48: =V48/(1-W48) -> 0 | Y48: 0 | Z48: 0.09 | AA48: =Y48/(1-Z48) -> 0
B49: Инпейнт (детальная доработка) | E49: 1 | F49: проект | G49: 1 | K49: =(E49*G49*H49)+(I49*J49*E49*G49) -> 0 | L49: 0.09 | M49: =K49/(1-L49) -> 0 | P49: 1 | Q49: проект | R49: 1 | V49: =(P49*R49*S49)+(T49*U49*P49*R49) -> 0 | W49: 0.09 | X49: =V49/(1-W49) -> 0 | Y49: 0 | Z49: 0.09 | AA49: =Y49/(1-Z49) -> 0
B50: Видео генерации | E50: 1 | F50: проект | G50: 1 | K50: =(E50*G50*H50)+(I50*J50*E50*G50) -> 0 | L50: 0.09 | M50: =K50/(1-L50) -> 0 | P50: 1 | Q50: проект | R50: 1 | V50: =(P50*R50*S50)+(T50*U50*P50*R50) -> 0 | W50: 0.09 | X50: =V50/(1-W50) -> 0 | Y50: 0 | Z50: 0.09 | AA50: =Y50/(1-Z50) -> 0
B51: Клинап | E51: 1 | F51: проект | G51: 1 | K51: =(E51*G51*H51)+(I51*J51*E51*G51) -> 0 | L51: 0.09 | M51: =K51/(1-L51) -> 0 | P51: 1 | Q51: проект | R51: 1 | V51: =(P51*R51*S51)+(T51*U51*P51*R51) -> 0 | W51: 0.09 | X51: =V51/(1-W51) -> 0 | Y51: 0 | Z51: 0.09 | AA51: =Y51/(1-Z51) -> 0
B52: Оплата лицензионных сервисов | E52: 1 | F52: проект | G52: 1 | K52: =(E52*G52*H52)+(I52*J52*E52*G52) -> 0 | L52: 0.09 | M52: =K52/(1-L52) -> 0 | P52: 1 | Q52: проект | R52: 1 | V52: =(P52*R52*S52)+(T52*U52*P52*R52) -> 0 | W52: 0.09 | X52: =V52/(1-W52) -> 0 | Y52: 0 | Z52: 0.09 | AA52: =Y52/(1-Z52) -> 0
B53: ЗВУК
B54: Стоковая музыка | E54: 1 | F54: шт | G54: 1 | K54: =(E54*G54*H54)+(I54*J54*E54*G54) -> 0 | L54: 0.09 | M54: =K54/(1-L54) -> 0 | P54: 1 | Q54: шт | R54: 1 | V54: =(P54*R54*S54)+(T54*U54*P54*R54) -> 0 | W54: 0.09 | X54: =V54/(1-W54) -> 0 | Y54: 0 | Z54: 0.09 | AA54: =Y54/(1-Z54) -> 0
B55: Композитор | E55: 1 | F55: проект | G55: 1 | K55: =(E55*G55*H55)+(I55*J55*E55*G55) -> 0 | L55: 0.09 | M55: =K55/(1-L55) -> 0 | P55: 1 | Q55: проект | R55: 1 | V55: =(P55*R55*S55)+(T55*U55*P55*R55) -> 0 | W55: 0.09 | X55: =V55/(1-W55) -> 0 | Y55: 0 | Z55: 0.09 | AA55: =Y55/(1-Z55) -> 0
B56: Диктор | E56: 1 | F56: проект | G56: 1 | K56: =(E56*G56*H56)+(I56*J56*E56*G56) -> 0 | L56: 0.09 | M56: =K56/(1-L56) -> 0 | P56: 1 | Q56: проект | R56: 1 | V56: =(P56*R56*S56)+(T56*U56*P56*R56) -> 0 | W56: 0.09 | X56: =V56/(1-W56) -> 0 | Y56: 0 | Z56: 0.09 | AA56: =Y56/(1-Z56) -> 0
B57: Студия звукозаписи | E57: 1 | F57: час | G57: 1 | K57: =(E57*G57*H57)+(I57*J57*E57*G57) -> 0 | L57: 0.09 | M57: =K57/(1-L57) -> 0 | P57: 1 | Q57: час | R57: 1 | V57: =(P57*R57*S57)+(T57*U57*P57*R57) -> 0 | W57: 0.09 | X57: =V57/(1-W57) -> 0 | Y57: 0 | Z57: 0.09 | AA57: =Y57/(1-Z57) -> 0
B58: Саунд-дизайн и сведение звука | E58: 1 | F58: ролик | G58: 1 | K58: =(E58*G58*H58)+(I58*J58*E58*G58) -> 0 | L58: 0.09 | M58: =K58/(1-L58) -> 0 | P58: 1 | Q58: ролик | R58: 1 | V58: =(P58*R58*S58)+(T58*U58*P58*R58) -> 0 | W58: 0.09 | X58: =V58/(1-W58) -> 0 | Y58: 0 | Z58: 0.09 | AA58: =Y58/(1-Z58) -> 0
L59: ИТОГО ПОСТ-ПРОИЗВОДСТВО | M59: =SUM(M24:M58) -> 0 | W59: ИТОГО ПОСТ-ПРОИЗВОДСТВО | X59: =SUM(X24:X58) -> 0 | Z59: ИТОГО ПОСТ-ПРОИЗВОДСТВО | AA59: =SUM(AA24:AA58) -> 0
L61: ПРОИЗВОДСТВО | M61: =M18+M21+M22 -> 0 | W61: ПРОИЗВОДСТВО | X61: =X18++X21+X22 -> 0 | Z61: ПРОИЗВОДСТВО | AA61: =AA18+AA21+AA22 -> 0
L62: ПОСТ-ПРОИЗВОДСТВО | M62: =M59 -> 0 | W62: ПОСТ-ПРОИЗВОДСТВО | X62: =X59 -> 0 | Z62: ПОСТ-ПРОИЗВОДСТВО | AA62: =AA59 -> 0
K63: НЕПРЕДВИДЕННЫЕ РАСХОДЫ | M63: =(M61+M62)*L63 -> 0 | W63: НЕПРЕДВИДЕННЫЕ РАСХОДЫ | X63: =M63 -> 0 | Z63: НЕПРЕДВИДЕННЫЕ РАСХОДЫ | AA63: 0
L64: ИТОГО ПРОИЗВОДСТВО | M64: =M61+M62+M63 -> 0 | W64: ИТОГО ПРОИЗВОДСТВО | X64: =X61+X62+X63 -> 0 | Z64: ИТОГО БЕЗ КРЕДИТОВАНИЯ | AA64: =AA61+AA62+AA63 -> 0
K65: МАРКАП | L65: 0.1 | M65: =M64*L65 -> 0
K66: КРЕДИТ, МЕСЯЦЕВ (4,5%) | L66: 0 | M66: =M64*L66*4.5% -> 0 | V66: КРЕДИТ, МЕСЯЦЕВ | W66: =L66 -> 0 | X66: =X64*W66*4.5%/2 -> 0 | Z66: КРЕДИТ, МЕСЯЦЕВ | AA66: =X66 -> 0
L67: ИТОГО ДО УСН | M67: =SUM(M64+M65+M66) -> 0 | W67: ИТОГО РАСХОДОВ ПО ПРОЕКТУ | X67: =SUM(X64+X66) -> 0 | Z67: ИТОГО РАСХОДОВ ПО ПРОЕКТУ | AA67: =SUM(AA64+AA66) -> 0
K68: НАЛОГ (УСН и НДС) | L68: 0.13 | M68: =(M67/0.87)-M67 -> 0
L69: ИТОГО С УСН | M69: =M67+M68 -> 0
B71: Примечания: | E71: - Смета актуальна для условий, указанных в продакшн подходе, а именно: права, даты съемок, даты запуска (подтверждения), даты сдача мастеров, творческой группы. В случае изменения любых условий смета может быть пересчитана. - При отмене, переносе или остановке проекта по вашей инициативе, вы берете на себя обязательства компенсировать все понесенные исполнителем расходы, а также обязательства перед подрядчиками исполнителя, возникшие на момент отмены, переноса или остановки проекта. - Если договор не будет подписан до съемочного дня, мы оставляем за собой право приостановить проект, при этом вы должны будете компенсировать все понесенные нами расходы, а также обязательства перед нашими подрядчиками, возникшие на тот момент. - В смете не учтены расходы на “погодный день”. | P71: ПРИБЫЛЬ (ПЛАН) | X71: =M67-X67 -> 0 | Y71: ПРИБЫЛЬ (ФАКТ) | AA71: =M67-AA67 -> 0
X72: =X71/M67 -> #DIV/0! | AA72: =AA71/M67 -> #DIV/0!

Sheet PASSPORT (ИП)
A1: ФИНАНСЫ И ДОКУМЕНТЫ – КЛИЕНТ
A2: Название проекта | B2: ПИК // AI ролики
A3: Наше юр лицо | B3: ИП Мельников
A4: Юр лицо клиента | B4: ПУБЛИЧНОЕ АКЦИОНЕРНОЕ ОБЩЕСТВО "ПИК-СПЕЦИАЛИЗИРОВАННЫЙ ЗАСТРОЙЩИК"
A5: Продюсер | B5: Гошко Вячеслав
A6: План IN-cost GROSS (с налогами) | B6: ='CE (ИП)'!X67 -> 0
A7: Факт IN-cost GROSS (с налогами) | B7: ='CE (ИП)'!AA67 -> 0
A8: OUT-cost GROSS (с налогами ИП) | B8: ='CE (ИП)'!M69 -> 0
A9: Плановая маржинальность (%) | B9: ='CE (ИП)'!T1 -> #DIV/0!
A10: Фактическая маржинальность (%) | B10: ='CE (ИП)'!AA72 -> #DIV/0!
A11: Финансовые условия: сроки и условия оплаты (сумма / пред- и постоплата / до какого числа каждая оплата) | B11: Постоплата в течение 30 календарных дней с даты подписания акта (дата акта 16.03)
A12: Ссылка на смету | B12: CE CULT x ПИК_AI ролики.xlsx
A13: Папка проекта | B13: https://drive.google.com/drive/folders/1f8Nnnirq8le4Mao-cEbzMREi8RZzKZYT
A14: Видеоролики
A15: Дата съемки | B15: без съёмки
A16: Дата сдачи результатов работ (выставления акта) | B16: 46094
A17: Конкретный подробный перечень услуг / виды работ | B17: Создание 1 видеоролика хронометражом до 60 секунд + 1 вертикальная версия до 60 секунд (доработка рендеров клиента, анимация рендеров, цк, саунд дизайн)
A18: Сроки начала и окончания работ | B18: 06.03.26-13.03.26
A19: Количество основных версий роликов | B19: 1
A20: Хронометраж каждой основной версии роликов | B20: до 60 сек.
A21: Количество монтажных версий роликов | B21: 2
A22: Хронометраж каждой монтажной версии роликов | B22: до 60 сек.
A23: Будут ли задействованы:
A24: - актеры | B24: нет
A25: - диктор | B25: нет
A26: - компьютерная графика | B26: нет
A27: Музыка:
A28: - композитор (если да, сколько пишеттреков и каким хронометражем) | B28: нет
A29: - стоковая | B29: да
A30: Объем прав:
A31: - сроки + дата начала использования роликов | B31: неисключительная лицензия
A32: - каналы распространения | B32: сайт клиента
A33: - территория | B33: РФ и весь мир (интернет)
A34: Фотографии
A35: Дата съемки
A36: Дата сдачи результатов работ (выставления акта)
A37: Конкретный подробный перечень услуг / виды работ
A38: Сроки начала и окончания работ
A39: Количество фото
A40: Объем прав:
A41: - сроки + дата начала использования роликов
A42: - каналы распространения
A43: - территория
A44: Радио / аудиоролики
A45: Дата сдачи результатов работ (выставления акта)
... A58: - стоковая
A59: Будут ли стоки: фото / видео. Если да, объем предоставляемых прав | B59: нет
A60: Что предоставляет Заказчик (сценарии, текст для озвучивания, актеров и т.д.) | B60: Рендеры своих объектов
A61: Прописать возможность архивного хранения ролика в интернете и соц сетях заказчика? | B61: да
A62: Прописать возможность создавать диркат? | B62: да
A63: Прописать возможность использования роликов в нашем портфолио, сайте, соц сетях (для нас и команды)? | B63: да

Sheet PASSPORT (ООО)
A1: ФИНАНСЫ И ДОКУМЕНТЫ – КЛИЕНТ
A2: Название проекта
A3: Наше юр лицо | B3: ООО "Культ"
A4: Юр лицо клиента
A5: Продюсер
A6: План IN-cost GROSS (с налогами) | B6: ='CE (ООО)'!X67 -> 0
A7: Факт IN-cost GROSS (с налогами) | B7: ='CE (ООО)'!AA67 -> 0
A8: OUT-cost NET (без НДС) | B8: ='CE (ООО)'!M67 -> 0
A9: OUT-cost GROSS (с НДС) | B9: ='CE (ООО)'!M69 -> 0
A10: Плановая маржинальность (%) | B10: =(B8-B6)/B8 -> #DIV/0!
A11: Фактическая маржинальность (%) | B11: ='CE (ООО)'!AA72 -> #DIV/0!
A12: Финансовые условия: сроки и условия оплаты (сумма / пред- и постоплата / до какого числа каждая оплата)
A13: Ссылка на смету
A14: Папка проекта
A15: Видеоролики
A16: Дата съемки
A17: Дата сдачи результатов работ (выставления акта)
A18: Конкретный подробный перечень услуг / виды работ
A19: Сроки начала и окончания работ
A20: Количество основных версий роликов
A21: Хронометраж каждой основной версии роликов
A22: Количество монтажных версий роликов
A23: Хронометраж каждой монтажной версии роликов
... A64: Прописать возможность использования роликов в нашем портфолио, сайте, соц сетях (для нас и команды)?

Sheet PASSPORT (допкост) (ООО)
A1: ФИНАНСЫ И ДОКУМЕНТЫ – КЛИЕНТ
A2: План IN-cost GROSS (с налогами) | B2: ='CE (ООО)'!X67 -> 0
A3: Факт IN-cost GROSS (с налогами) | B3: ='CE (ООО)'!AA67 -> 0
A4: OUT-cost NET (без НДС) | B4: ='CE (ООО)'!M67 -> 0
A5: OUT-cost GROSS (с НДС) | B5: ='CE (ООО)'!M69 -> 0
A6: Плановая маржинальность (%) | B6: =(B4-B2)/B4 -> #DIV/0!
A7: Фактическая маржинальность (%) | B7: ='CE (ООО)'!AA72 -> #DIV/0!
A8: Финансовые условия: сроки и условия оплаты (сумма / пред- и постоплата / до какого числа каждая оплата)
A9: Конкретный подробный перечень доп услуг / виды доп работ
A10: Сроки начала и окончания доп работ
A11: РИД. Какие РИД создавались?
A12: - новые РИД не возникают
A13: - актеры
A14: - диктор
A15: - компьютерная графика
A16: Музыка:
A17: - композитор (если да, сколько пишет треков и каким хронометражем)
A18: - стоковая
A19: Объем прав:
... A44: - территория

Sheet ПЕРЕРАБОТКИ
A1: РАСЧЕТ ПЕРЕРАБОТОК | B1: Смена | C1: Вызов до мотора: режиссер, второй режиссер, оператор и фокус | D1: Вызов до мотора и выход: механики и остальной тех. персонал | E1: Вызов до мотора и выход: бригада осветителей и постановщиков | F1: Текущий обед | G1: За МКАД
B2: 12 | C2: 0 | D2: 3 | E2: 4 | F2: 1 | G2: 0
A5: наименование единицы | B5: смена/час | C5: переработки | G5: всего часов переработки
C6: часы | D6: вызов до смены | E6: текущий обед | F6: за МКАД
A7: Режиссер | B7: 16 | C7: =B2-B7 -> -4 | D7: =C2 -> 0 | E7: =F2 -> 1 | F7: =G2 -> 0 | G7: =C7+D7+E7+F7 -> -3
A8: Второй режиссер | B8: 16 | C8: =B2-B8 -> -4 | D8: =C2 -> 0 | E8: =F2 -> 1 | F8: =G2 -> 0 | G8: =C8+D8+E8+F8 -> -3
A9: Оператор-постановщик | B9: 12 | C9: =B2-B9 -> 0 | D9: =C2 -> 0 | E9: =F2 -> 1 | F9: =G2 -> 0 | G9: =C9+D9+E9+F9 -> 1
A11: Фокус-пуллер | B11: 10 | C11: =B2-B11 -> 2 | D11: =C2 -> 0 | E11: =F2 -> 1 | F11: =G2 -> 0 | G11: =C11+D11+E11+F11 -> 3
A12: Механики камеры | B12: 10 | C12: =B2-B12 -> 2 | D12: =D2 -> 3 | E12: =F2 -> 1 | F12: =G2 -> 0 | G12: =C12+D12+E12+F12 -> 6
A13: Бригада осветителей | B13: 10 | C13: =B2-B13 -> 2 | D13: =E2 -> 4 | E13: =F2 -> 1 | F13: =G2 -> 0 | G13: =C13+D13+E13+F13 -> 7
A14: Механики долли/крана | B14: 10 | C14: =B2-B14 -> 2 | D14: =D2 -> 3 | E14: =F2 -> 1 | F14: =G2 -> 0 | G14: =C14+D14+E14+F14 -> 6
A15: Стедикам/гимбл/дрон | B15: 8 | C15: =B2-B15 -> 4 | D15: =D2 -> 3 | E15: =F2 -> 1 | F15: =G2 -> 0 | G15: =C15+D15+E15+F15 -> 8
A16: Motion Control | B16: 8 | C16: =B2-B16 -> 4 | D16: =D2 -> 3 | E16: =F2 -> 1 | F16: =G2 -> 0 | G16: =C16+D16+E16+F16 -> 8
A18: Звукорежиссер/Гример/Ассистент | B18: 10 | C18: =B2-B18 -> 2 | D18: =D2 -> 3 | E18: =F2 -> 1 | F18: =G2 -> 0 | G18: =C18+D18+E18+F18 -> 6
A19: Реквизитор/постановщик | B19: 8 | C19: =B2-B19 -> 4 | D19: =E2 -> 4 | E19: =F9 -> 0 | F19: =G2 -> 0 | G19: =C19+D19+E19+F19 -> 8
A20: SFX/VFX | B20: 10 | C20: =B2-B20 -> 2 | D20: =D2 -> 3 | E20: =F2 -> 1 | F20: =G2 -> 0 | G20: =C20+D20+E20+F20 -> 6
A22: Аренда локации | B22: 12 | C22: =B2-B22 -> 0 | D22: =E2 -> 4 | E22: 0 | F22: 0 | G22: =C22+D22+E22+F22 -> 4
A23: Транспорт (светобаза, гриптрак, гена и т.д.) | B23: 10 | C23: =B2-B23 -> 2 | D23: =E2 -> 4 | E23: 0 | F23: =G2 -> 0 | G23: =C23+D23+E23+F23 -> 6
A24: Транспорт (камерваген, гримваген и т.д.) | B24: 10 | C24: =B2-B24 -> 2 | D24: =D2 -> 3 | E24: =F2 -> 1 | F24: =G2 -> 0 | G24: =C24+D24+E24+F24 -> 6
