Workbook

Sheet CE (ООО)
K1: ИТОГО, ДО НДС | M1: =M279 -> 2582186.2 | O1: IN COST | P1: ЦЕЛЬ | R1: 0.2 | S1: МАРЖ–ТЬ (ПЛАН) | T1: =X284 -> 0.14853198 | U1: IN-COST (ПЛАН) | V1: =X276 -> 2103970.3 | X1: МАРЖ-ТЬ (ФАКТ) | Y1: =AA284 -> 0.96333391 | Z1: IN-COST (ФАКТ) | AA1: =AA279 -> 94678.665
C2: Название проекта | E2: кол-во | F2: наименование единицы | G2: единица | H2: цена за единицу | I2: переработки (всего) | K2: подытог | L2: налоговая ставка | M2: итого c налогами | N2: комментарии | P2: кол-во | Q2: наименование единицы | R2: единица | S2: цена за единицу | T2: переработки (всего) | V2: подытог (ПЛАН) | W2: Налоговая ставка | X2: Итого c налогами (ПЛАН) | Y2: подытог (ФАКТ) | Z2: налог | AA2: Итого c налогами (ФАКТ)
A4: Съемочных дней | D4: 1 | I4: часы | J4: ставка | T4: часы | U4: ставка
A5: Съемочных часов | D5: 12
A7: A. РАЗРАБОТКА
B8: Разработка креатива | E8: 1 | F8: проект | G8: 1 | K8: =(E8*G8*H8)+(I8*J8*E8*G8) -> 0 | L8: 0.09 | M8: =K8/(1-L8) -> 0 | P8: 1 | Q8: проект | R8: 1 | V8: =(P8*R8*S8)+(T8*U8*P8*R8) -> 0 | W8: 0.09 | X8: =V8/(1-W8) -> 0 | Y8: 0 | Z8: 0.09 | AA8: =Y8/(1-Z8) -> 0
B9: Креативный супервайзинг проекта | E9: 1 | F9: проект | G9: 1 | H9: 3500 | K9: =(E9*G9*H9)+(I9*J9*E9*G9) -> 3500 | L9: 0.09 | M9: =K9/(1-L9) -> 3846.1538 | P9: 1 | Q9: проект | R9: 1 | V9: =(P9*R9*S9)+(T9*U9*P9*R9) -> 0 | W9: 0.09 | X9: =V9/(1-W9) -> 0 | Y9: 0 | Z9: 0.09 | AA9: =Y9/(1-Z9) -> 0
B10: Директорс рисёрч | E10: 1 | F10: проект | G10: 1 | K10: =(E10*G10*H10)+(I10*J10*E10*G10) -> 0 | L10: 0.09 | M10: =K10/(1-L10) -> 0 | P10: 1 | Q10: проект | R10: 1 | V10: =(P10*R10*S10)+(T10*U10*P10*R10) -> 0 | W10: 0.09 | X10: =V10/(1-W10) -> 0 | Y10: 0 | Z10: 0.09 | AA10: =Y10/(1-Z10) -> 0
B11: Оформление тритмента | E11: 1 | F11: проект | G11: 1 | K11: =(E11*G11*H11)+(I11*J11*E11*G11) -> 0 | L11: 0.09 | M11: =K11/(1-L11) -> 0 | P11: 1 | Q11: проект | R11: 1 | V11: =(P11*R11*S11)+(T11*U11*P11*R11) -> 0 | W11: 0.09 | X11: =V11/(1-W11) -> 0 | Y11: 0 | Z11: 0.09 | AA11: =Y11/(1-Z11) -> 0
B12: Раскадровка | E12: 1 | F12: кадр | G12: 1 | K12: =(E12*G12*H12)+(I12*J12*E12*G12) -> 0 | L12: 0.09 | M12: =K12/(1-L12) -> 0 | P12: 1 | Q12: кадр | R12: 1 | V12: =(P12*R12*S12)+(T12*U12*P12*R12) -> 0 | W12: 0.09 | X12: =V12/(1-W12) -> 0 | Y12: 0 | Z12: 0.09 | AA12: =Y12/(1-Z12) -> 0
B13: Аниматик | E13: 1 | F13: проект | G13: 1 | K13: =(E13*G13*H13)+(I13*J13*E13*G13) -> 0 | L13: 0.09 | M13: =K13/(1-L13) -> 0 | P13: 1 | Q13: проект | R13: 1 | V13: =(P13*R13*S13)+(T13*U13*P13*R13) -> 0 | W13: 0.09 | X13: =V13/(1-W13) -> 0 | Y13: 0 | Z13: 0.09 | AA13: =Y13/(1-Z13) -> 0
B14: ППМ-буклеты | E14: 1 | F14: проект | G14: 1 | K14: =(E14*G14*H14)+(I14*J14*E14*G14) -> 0 | L14: 0.09 | M14: =K14/(1-L14) -> 0 | P14: 1 | Q14: проект | R14: 1 | V14: =(P14*R14*S14)+(T14*U14*P14*R14) -> 0 | W14: 0.09 | X14: =V14/(1-W14) -> 0 | Y14: 0 | Z14: 0.09 | AA14: =Y14/(1-Z14) -> 0
B15: Переводчик | E15: 1 | F15: проект | G15: 1 | K15: =(E15*G15*H15)+(I15*J15*E15*G15) -> 0 | L15: 0.09 | M15: =K15/(1-L15) -> 0 | P15: 1 | Q15: проект | R15: 1 | V15: =(P15*R15*S15)+(T15*U15*P15*R15) -> 0 | W15: 0.09 | X15: =V15/(1-W15) -> 0 | Y15: 0 | Z15: 0.09 | AA15: =Y15/(1-Z15) -> 0
B16: Юридическое сопровождение | E16: 1 | F16: проект | G16: 1 | K16: =(E16*G16*H16)+(I16*J16*E16*G16) -> 0 | L16: 0.09 | M16: =K16/(1-L16) -> 0 | P16: 1 | Q16: проект | R16: 1 | V16: =(P16*R16*S16)+(T16*U16*P16*R16) -> 0 | W16: 0.09 | X16: =V16/(1-W16) -> 0 | Y16: 0 | Z16: 0.09 | AA16: =Y16/(1-Z16) -> 0
B17: Курьер, почтовые расходы | E17: 1 | F17: проект | G17: 1 | K17: =(E17*G17*H17)+(I17*J17*E17*G17) -> 0 | L17: 0.09 | M17: =K17/(1-L17) -> 0 | P17: 1 | Q17: проект | R17: 1 | V17: =(P17*R17*S17)+(T17*U17*P17*R17) -> 0 | W17: 0.09 | X17: =V17/(1-W17) -> 0 | Y17: 0 | Z17: 0.09 | AA17: =Y17/(1-Z17) -> 0
L18: ИТОГО РАЗРАБОТКА | M18: =SUM(M8:M17) -> 3846.1538 | W18: ИТОГО РАЗРАБОТКА | X18: =SUM(X8:X17) -> 0 | Z18: ИТОГО РАЗРАБОТКА | AA18: =SUM(AA8:AA17) -> 0
A20: B. ПРЕДПРОИЗВОДСТВЕННАЯ ПОДГОТОВКА
B21: ПОДБОР ЛОКАЦИИ
B22: Локейшн-менеджер | E22: 1 | F22: проект | G22: 1 | K22: =(E22*G22*H22)+(I22*J22*E22*G22) -> 0 | L22: 0.09 | M22: =K22/(1-L22) -> 0 | P22: 1 | Q22: проект | R22: 1 | V22: =(P22*R22*S22)+(T22*U22*P22*R22) -> 0 | W22: 0.09 | X22: =V22/(1-W22) -> 0 | Y22: 0 | Z22: 0.09 | AA22: =Y22/(1-Z22) -> 0
B23: Микроавтобус | E23: 1 | F23: смена | G23: 1 | K23: =(E23*G23*H23)+(I23*J23*E23*G23) -> 0 | L23: 0.09 | M23: =K23/(1-L23) -> 0 | P23: 1 | Q23: смена | R23: 1 | V23: =(P23*R23*S23)+(T23*U23*P23*R23) -> 0 | W23: 0.09 | X23: =V23/(1-W23) -> 0 | Y23: 0 | Z23: 0.09 | AA23: =Y23/(1-Z23) -> 0
B24: КАСТИНГ
B25: Кастинг-директор | E25: 1 | F25: проект | G25: 1 | K25: =(E25*G25*H25)+(I25*J25*E25*G25) -> 0 | L25: 0.09 | M25: =K25/(1-L25) -> 0 | P25: 1 | Q25: проект | R25: 1 | V25: =(P25*R25*S25)+(T25*U25*P25*R25) -> 0 | W25: 0.09 | X25: =V25/(1-W25) -> 0 | Y25: 0 | Z25: 0.09 | AA25: =Y25/(1-Z25) -> 0
B26: Аренда студии | E26: 1 | F26: час | G26: 1 | K26: =(E26*G26*H26)+(I26*J26*E26*G26) -> 0 | L26: 0.09 | M26: =K26/(1-L26) -> 0 | P26: 1 | Q26: час | R26: 1 | V26: =(P26*R26*S26)+(T26*U26*P26*R26) -> 0 | W26: 0.09 | X26: =V26/(1-W26) -> 0 | Y26: 0 | Z26: 0.09 | AA26: =Y26/(1-Z26) -> 0
B27: Оператор | E27: 1 | F27: час | G27: 1 | K27: =(E27*G27*H27)+(I27*J27*E27*G27) -> 0 | L27: 0.09 | M27: =K27/(1-L27) -> 0 | P27: 1 | Q27: час | R27: 1 | V27: =(P27*R27*S27)+(T27*U27*P27*R27) -> 0 | W27: 0.09 | X27: =V27/(1-W27) -> 0 | Y27: 0 | Z27: 0.09 | AA27: =Y27/(1-Z27) -> 0
B28: Аренда съемочного оборудования | E28: 1 | F28: смена | G28: 1 | K28: =(E28*G28*H28)+(I28*J28*E28*G28) -> 0 | L28: 0.09 | M28: =K28/(1-L28) -> 0 | P28: 1 | Q28: смена | R28: 1 | V28: =(P28*R28*S28)+(T28*U28*P28*R28) -> 0 | W28: 0.09 | X28: =V28/(1-W28) -> 0 | Y28: 0 | Z28: 0.09 | AA28: =Y28/(1-Z28) -> 0
L29: ИТОГО ПРЕДПРОИЗВОДСТВЕННАЯ ПОДГОТОВКА | M29: =SUM(M22:M28) -> 0 | W29: ИТОГО ПРЕДПРОИЗВОДСТВЕННАЯ ПОДГОТОВКА | X29: =SUM(X22:X28) -> 0 | Z29: ИТОГО ПРЕДПРОИЗВОДСТВЕННАЯ ПОДГОТОВКА | AA29: =SUM(AA22:AA28) -> 0
A31: C. АКТЕРЫ
B32: Основной актер | E32: 1 | F32: смена | G32: 1 | K32: =(E32*G32*H32)+(I32*J32*E32*G32) -> 0 | L32: 0.09 | M32: =K32/(1-L32) -> 0 | P32: 1 | Q32: смена | R32: 1 | V32: =(P32*R32*S32)+(T32*U32*P32*R32) -> 0 | W32: 0.09 | X32: =V32/(1-W32) -> 0 | Y32: 0 | Z32: 0.09 | AA32: =Y32/(1-Z32) -> 0
B33: Второстепенный актер | E33: 1 | F33: смена | G33: 1 | K33: =(E33*G33*H33)+(I33*J33*E33*G33) -> 0 | L33: 0.09 | M33: =K33/(1-L33) -> 0 | P33: 1 | Q33: смена | R33: 1 | V33: =(P33*R33*S33)+(T33*U33*P33*R33) -> 0 | W33: 0.09 | X33: =V33/(1-W33) -> 0 | Y33: 0 | Z33: 0.09 | AA33: =Y33/(1-Z33) -> 0
B34: Массовка | E34: 1 | F34: смена | G34: 1 | K34: =(E34*G34*H34)+(I34*J34*E34*G34) -> 0 | L34: 0.09 | M34: =K34/(1-L34) -> 0 | P34: 1 | Q34: смена | R34: 1 | V34: =(P34*R34*S34)+(T34*U34*P34*R34) -> 0 | W34: 0.09 | X34: =V34/(1-W34) -> 0 | Y34: 0 | Z34: 0.09 | AA34: =Y34/(1-Z34) -> 0
B35: Ассистент по актерам | E35: 1 | F35: смена | G35: 1 | H35: 12000 | J35: 1500 | K35: =(E35*G35*H35)+(I35*J35*E35*G35) -> 12000 | L35: 0.09 | M35: =K35/(1-L35) -> 13186.813 | P35: 1 | Q35: смена | R35: 1 | S35: 12000 | U35: 1500 | V35: =(P35*R35*S35)+(T35*U35*P35*R35) -> 12000 | W35: 0.09 | X35: =V35/(1-W35) -> 13186.813 | Y35: 0 | Z35: 0.09 | AA35: =Y35/(1-Z35) -> 0
B36: Бригадир массовки (подбор + площадка) | E36: 1 | F36: смена | G36: 1 | K36: =(E36*G36*H36)+(I36*J36*E36*G36) -> 0 | L36: 0.09 | M36: =K36/(1-L36) -> 0 | P36: 1 | Q36: смена | R36: 1 | V36: =(P36*R36*S36)+(T36*U36*P36*R36) -> 0 | W36: 0.09 | X36: =V36/(1-W36) -> 0 | Y36: 0 | Z36: 0.09 | AA36: =Y36/(1-Z36) -> 0
L37: ИТОГО АКТЕРЫ | M37: =SUM(M32:M36) -> 13186.813 | W37: ИТОГО АКТЕРЫ | X37: =SUM(X32:X36) -> 13186.813 | Z37: ИТОГО АКТЕРЫ | AA37: =SUM(AA32:AA36) -> 0
A39: D. ГОНОРАРЫ
B40: ПРОДЮСЕРЫ И АДМИНИСТРАЦИЯ
B41: Исполнительный продюсер | E41: 1 | F41: проект | G41: 1 | H41: 200000 | K41: =(E41*G41*H41)+(I41*J41*E41*G41) -> 200000 | L41: 0.09 | M41: =K41/(1-L41) -> 219780.22 | P41: 1 | Q41: проект | R41: 1 | S41: 200000 | V41: =(P41*R41*S41)+(T41*U41*P41*R41) -> 200000 | W41: 0.09 | X41: =V41/(1-W41) -> 219780.22 | Y41: 0 | Z41: 0.09 | AA41: =Y41/(1-Z41) -> 0
B42: Линейный продюсер | E42: 1 | F42: проект | G42: 1 | K42: =(E42*G42*H42)+(I42*J42*E42*G42) -> 0 | L42: 0.09 | M42: =K42/(1-L42) -> 0 | P42: 1 | Q42: проект | R42: 1 | V42: =(P42*R42*S42)+(T42*U42*P42*R42) -> 0 | W42: 0.09 | X42: =V42/(1-W42) -> 0 | Y42: 0 | Z42: 0.09 | AA42: =Y42/(1-Z42) -> 0
B43: Ассистент продюсера | E43: 1 | F43: проект | G43: 1 | K43: =(E43*G43*H43)+(I43*J43*E43*G43) -> 0 | L43: 0.09 | M43: =K43/(1-L43) -> 0 | P43: 1 | Q43: проект | R43: 1 | V43: =(P43*R43*S43)+(T43*U43*P43*R43) -> 0 | W43: 0.09 | X43: =V43/(1-W43) -> 0 | Y43: 0 | Z43: 0.09 | AA43: =Y43/(1-Z43) -> 0
B44: Директор группы | E44: 1 | F44: проект | G44: 1 | H44: 150000 | K44: =(E44*G44*H44)+(I44*J44*E44*G44) -> 150000 | L44: 0.09 | M44: =K44/(1-L44) -> 164835.16 | P44: 1 | Q44: проект | R44: 1 | S44: 150000 | V44: =(P44*R44*S44)+(T44*U44*P44*R44) -> 150000 | W44: 0.09 | X44: =V44/(1-W44) -> 164835.16 | Y44: 0 | Z44: 0.09 | AA44: =Y44/(1-Z44) -> 0
B45: Заместитель директора | E45: 1 | F45: проект | G45: 1 | H45: 75000 | K45: =(E45*G45*H45)+(I45*J45*E45*G45) -> 75000 | L45: 0.09 | M45: =K45/(1-L45) -> 82417.582 | P45: 1 | Q45: проект | R45: 1 | S45: 75000 | V45: =(P45*R45*S45)+(T45*U45*P45*R45) -> 75000 | W45: 0.09 | X45: =V45/(1-W45) -> 82417.582 | Y45: 0 | Z45: 0.09 | AA45: =Y45/(1-Z45) -> 0
B46: Администратор | E46: 1 | F46: смена | G46: 1 | H46: 25000 | K46: =(E46*G46*H46)+(I46*J46*E46*G46) -> 25000 | L46: 0.09 | M46: =K46/(1-L46) -> 27472.527 | P46: 1 | Q46: смена | R46: 1 | S46: 25000 | V46: =(P46*R46*S46)+(T46*U46*P46*R46) -> 25000 | W46: 0.09 | X46: =V46/(1-W46) -> 27472.527 | Y46: 0 | Z46: 0.09 | AA46: =Y46/(1-Z46) -> 0
B47: Рабочие | E47: 1 | F47: смена | G47: 1 | H47: 7000 | J47: 700 | K47: =(E47*G47*H47)+(I47*J47*E47*G47) -> 7000 | L47: 0.09 | M47: =K47/(1-L47) -> 7692.3077 | P47: 1 | Q47: смена | R47: 1 | S47: 7000 | U47: 700 | V47: =(P47*R47*S47)+(T47*U47*P47*R47) -> 7000 | W47: 0.09 | X47: =V47/(1-W47) -> 7692.3077 | Y47: 0 | Z47: 0.09 | AA47: =Y47/(1-Z47) -> 0
B48: РЕЖИССЕРСКИЙ ДЕПАРТАМЕНТ
B49: Режиссер | E49: 1 | F49: проект | G49: 1 | K49: =(E49*G49*H49)+(I49*J49*E49*G49) -> 0 | L49: 0.09 | M49: =K49/(1-L49) -> 0 | P49: 1 | Q49: проект | R49: 1 | V49: =(P49*R49*S49)+(T49*U49*P49*R49) -> 0 | W49: 0.09 | X49: =V49/(1-W49) -> 0 | Y49: 0 | Z49: 0.09 | AA49: =Y49/(1-Z49) -> 0
B50: Второй режиссер | E50: 1 | F50: проект | G50: 1 | K50: =(E50*G50*H50)+(I50*J50*E50*G50) -> 0 | L50: 0.09 | M50: =K50/(1-L50) -> 0 | P50: 1 | Q50: проект | R50: 1 | V50: =(P50*R50*S50)+(T50*U50*P50*R50) -> 0 | W50: 0.09 | X50: =V50/(1-W50) -> 0 | Y50: 0 | Z50: 0.09 | AA50: =Y50/(1-Z50) -> 0
B51: Хлопушка | E51: 1 | F51: смена | G51: 1 | K51: =(E51*G51*H51)+(I51*J51*E51*G51) -> 0 | L51: 0.09 | M51: =K51/(1-L51) -> 0 | P51: 1 | Q51: смена | R51: 1 | V51: =(P51*R51*S51)+(T51*U51*P51*R51) -> 0 | W51: 0.09 | X51: =V51/(1-W51) -> 0 | Y51: 0 | Z51: 0.09 | AA51: =Y51/(1-Z51) -> 0
B52: Монтажер на площадке | E52: 1 | F52: час | G52: 1 | K52: =(E52*G52*H52)+(I52*J52*E52*G52) -> 0 | L52: 0.09 | M52: =K52/(1-L52) -> 0 | P52: 1 | Q52: час | R52: 1 | V52: =(P52*R52*S52)+(T52*U52*P52*R52) -> 0 | W52: 0.09 | X52: =V52/(1-W52) -> 0 | Y52: 0 | Z52: 0.09 | AA52: =Y52/(1-Z52) -> 0
B53: ОПЕРАТОРСКАЯ ГРУППА
B54: Оператор-постановщик | E54: 1 | F54: смена | G54: 1 | H54: 200000 | J54: 20000 | K54: =(E54*G54*H54)+(I54*J54*E54*G54) -> 200000 | L54: 0.09 | M54: =K54/(1-L54) -> 219780.22 | P54: 1 | Q54: смена | R54: 1 | S54: 200000 | U54: 20000 | V54: =(P54*R54*S54)+(T54*U54*P54*R54) -> 200000 | W54: 0.09 | X54: =V54/(1-W54) -> 219780.22 | Y54: 0 | Z54: 0.09 | AA54: =Y54/(1-Z54) -> 0
B55: — прогрессивные переработки с 17 по 22 час | E55: 1 | F55: час | G55: 1 | J55: 40000 | K55: =(E55*G55*H55)+(I55*J55*E55*G55) -> 0 | L55: 0.09 | M55: =K55/(1-L55) -> 0 | P55: 1 | Q55: час | R55: 1 | U55: 40000 | V55: =(P55*R55*S55)+(T55*U55*P55*R55) -> 0 | W55: 0.09 | X55: =V55/(1-W55) -> 0 | Y55: 0 | Z55: 0.09 | AA55: =Y55/(1-Z55) -> 0
B56: — прогрессивные переработки с 23 часа | E56: 1 | F56: час | G56: 1 | J56: 80000 | K56: =(E56*G56*H56)+(I56*J56*E56*G56) -> 0 | L56: 0.09 | M56: =K56/(1-L56) -> 0 | P56: 1 | Q56: час | R56: 1 | U56: 80000 | V56: =(P56*R56*S56)+(T56*U56*P56*R56) -> 0 | W56: 0.09 | X56: =V56/(1-W56) -> 0 | Y56: 0 | Z56: 0.09 | AA56: =Y56/(1-Z56) -> 0
B57: Фокус-пуллер | E57: 1 | F57: смена | G57: 1 | H57: 34000 | J57: 5000 | K57: =(E57*G57*H57)+(I57*J57*E57*G57) -> 34000 | L57: 0.09 | M57: =K57/(1-L57) -> 37362.637 | P57: 1 | Q57: смена | R57: 1 | S57: 34000 | U57: 5000 | V57: =(P57*R57*S57)+(T57*U57*P57*R57) -> 34000 | W57: 0.09 | X57: =V57/(1-W57) -> 37362.637 | Y57: 0 | Z57: 0.09 | AA57: =Y57/(1-Z57) -> 0
B58: — прогрессивные переработки с 17 по 22 час | E58: 1 | F58: час | G58: 1 | J58: 10000 | K58: =(E58*G58*H58)+(I58*J58*E58*G58) -> 0 | L58: 0.09 | M58: =K58/(1-L58) -> 0 | P58: 1 | Q58: час | R58: 1 | U58: 10000 | V58: =(P58*R58*S58)+(T58*U58*P58*R58) -> 0 | W58: 0.09 | X58: =V58/(1-W58) -> 0 | Y58: 0 | Z58: 0.09 | AA58: =Y58/(1-Z58) -> 0
B59: — прогрессивные переработки с 23 часа | E59: 1 | F59: час | G59: 1 | J59: 20000 | K59: =(E59*G59*H59)+(I59*J59*E59*G59) -> 0 | L59: 0.09 | M59: =K59/(1-L59) -> 0 | P59: 1 | Q59: час | R59: 1 | U59: 20000 | V59: =(P59*R59*S59)+(T59*U59*P59*R59) -> 0 | W59: 0.09 | X59: =V59/(1-W59) -> 0 | Y59: 0 | Z59: 0.09 | AA59: =Y59/(1-Z59) -> 0
B60: Механики камеры | E60: 1 | F60: смена | G60: 2 | H60: 18000 | J60: 3500 | K60: =(E60*G60*H60)+(I60*J60*E60*G60) -> 36000 | L60: 0.09 | M60: =K60/(1-L60) -> 39560.44 | P60: 1 | Q60: смена | R60: 2 | S60: 18000 | U60: 3500 | V60: =(P60*R60*S60)+(T60*U60*P60*R60) -> 36000 | W60: 0.09 | X60: =V60/(1-W60) -> 39560.44 | Y60: 0 | Z60: 0.09 | AA60: =Y60/(1-Z60) -> 0
B61: — прогрессивные переработки с 17 по 22 час | E61: 1 | F61: час | G61: 1 | J61: 7000 | K61: =(E61*G61*H61)+(I61*J61*E61*G61) -> 0 | L61: 0.09 | M61: =K61/(1-L61) -> 0 | P61: 1 | Q61: час | R61: 1 | U61: 7000 | V61: =(P61*R61*S61)+(T61*U61*P61*R61) -> 0 | W61: 0.09 | X61: =V61/(1-W61) -> 0 | Y61: 0 | Z61: 0.09 | AA61: =Y61/(1-Z61) -> 0
B62: — прогрессивные переработки с 23 часа | E62: 1 | F62: час | G62: 1 | J62: 14000 | K62: =(E62*G62*H62)+(I62*J62*E62*G62) -> 0 | L62: 0.09 | M62: =K62/(1-L62) -> 0 | P62: 1 | Q62: час | R62: 1 | U62: 14000 | V62: =(P62*R62*S62)+(T62*U62*P62*R62) -> 0 | W62: 0.09 | X62: =V62/(1-W62) -> 0 | Y62: 0 | Z62: 0.09 | AA62: =Y62/(1-Z62) -> 0
B63: — погрузка/разгрузка | E63: 1 | F63: смена | G63: 1 | H63: 14000 | K63: =(E63*G63*H63)+(I63*J63*E63*G63) -> 14000 | L63: 0.09 | M63: =K63/(1-L63) -> 15384.615 | P63: 1 | Q63: смена | R63: 1 | S63: 14000 | V63: =(P63*R63*S63)+(T63*U63*P63*R63) -> 14000 | W63: 0.09 | X63: =V63/(1-W63) -> 15384.615 | Y63: 0 | Z63: 0.09 | AA63: =Y63/(1-Z63) -> 0
B64: — расходники | E64: 1 | F64: смена | G64: 1 | H64: 3000 | K64: =(E64*G64*H64)+(I64*J64*E64*G64) -> 3000 | L64: 0.09 | M64: =K64/(1-L64) -> 3296.7033 | P64: 1 | Q64: смена | R64: 1 | S64: 3000 | V64: =(P64*R64*S64)+(T64*U64*P64*R64) -> 3000 | W64: 0.09 | X64: =V64/(1-W64) -> 3296.7033 | Y64: 0 | Z64: 0.09 | AA64: =Y64/(1-Z64) -> 0
B65: Гафер (освоение) | E65: 1 | F65: смена | G65: 1 | H65: 20000 | K65: =(E65*G65*H65)+(I65*J65*E65*G65) -> 20000 | L65: 0.09 | M65: =K65/(1-L65) -> 21978.022 | P65: 1 | Q65: смена | R65: 1 | S65: 20000 | V65: =(P65*R65*S65)+(T65*U65*P65*R65) -> 20000 | W65: 0.09 | X65: =V65/(1-W65) -> 21978.022 | Y65: 0 | Z65: 0.09 | AA65: =Y65/(1-Z65) -> 0
B66: Гафер | E66: 1 | F66: смена | G66: 1 | H66: 20000 | J66: 4000 | K66: =(E66*G66*H66)+(I66*J66*E66*G66) -> 20000 | L66: 0.09 | M66: =K66/(1-L66) -> 21978.022 | P66: 1 | Q66: смена | R66: 1 | S66: 20000 | U66: 4000 | V66: =(P66*R66*S66)+(T66*U66*P66*R66) -> 20000 | W66: 0.09 | X66: =V66/(1-W66) -> 21978.022 | Y66: 0 | Z66: 0.09 | AA66: =Y66/(1-Z66) -> 0
B67: — прогрессивные переработки с 17 по 22 час | E67: 1 | F67: час | G67: 1 | J67: 8000 | K67: =(E67*G67*H67)+(I67*J67*E67*G67) -> 0 | L67: 0.09 | M67: =K67/(1-L67) -> 0 | P67: 1 | Q67: час | R67: 1 | U67: 8000 | V67: =(P67*R67*S67)+(T67*U67*P67*R67) -> 0 | W67: 0.09 | X67: =V67/(1-W67) -> 0 | Y67: 0 | Z67: 0.09 | AA67: =Y67/(1-Z67) -> 0
B68: — прогрессивные переработки с 23 часа | E68: 1 | F68: час | G68: 1 | J68: 16000 | K68: =(E68*G68*H68)+(I68*J68*E68*G68) -> 0 | L68: 0.09 | M68: =K68/(1-L68) -> 0 | P68: 1 | Q68: час | R68: 1 | U68: 16000 | V68: =(P68*R68*S68)+(T68*U68*P68*R68) -> 0 | W68: 0.09 | X68: =V68/(1-W68) -> 0 | Y68: 0 | Z68: 0.09 | AA68: =Y68/(1-Z68) -> 0
B69: Кей-грип | E69: 1 | F69: смена | G69: 1 | H69: 14000 | J69: 3200 | K69: =(E69*G69*H69)+(I69*J69*E69*G69) -> 14000 | L69: 0.09 | M69: =K69/(1-L69) -> 15384.615 | P69: 1 | Q69: смена | R69: 1 | S69: 14000 | U69: 3200 | V69: =(P69*R69*S69)+(T69*U69*P69*R69) -> 14000 | W69: 0.09 | X69: =V69/(1-W69) -> 15384.615 | Y69: 0 | Z69: 0.09 | AA69: =Y69/(1-Z69) -> 0
B70: — прогрессивные переработки с 17 по 22 час | E70: 1 | F70: час | G70: 1 | J70: 6400 | K70: =(E70*G70*H70)+(I70*J70*E70*G70) -> 0 | L70: 0.09 | M70: =K70/(1-L70) -> 0 | P70: 1 | Q70: час | R70: 1 | U70: 6400 | V70: =(P70*R70*S70)+(T70*U70*P70*R70) -> 0 | W70: 0.09 | X70: =V70/(1-W70) -> 0 | Y70: 0 | Z70: 0.09 | AA70: =Y70/(1-Z70) -> 0
B71: — прогрессивные переработки с 23 часа | E71: 1 | F71: час | G71: 1 | J71: 12800 | K71: =(E71*G71*H71)+(I71*J71*E71*G71) -> 0 | L71: 0.09 | M71: =K71/(1-L71) -> 0 | P71: 1 | Q71: час | R71: 1 | U71: 12800 | V71: =(P71*R71*S71)+(T71*U71*P71*R71) -> 0 | W71: 0.09 | X71: =V71/(1-W71) -> 0 | Y71: 0 | Z71: 0.09 | AA71: =Y71/(1-Z71) -> 0
B72: Бест-бой | E72: 1 | F72: смена | G72: 1 | H72: 14000 | J72: 3200 | K72: =(E72*G72*H72)+(I72*J72*E72*G72) -> 14000 | L72: 0.09 | M72: =K72/(1-L72) -> 15384.615 | P72: 1 | Q72: смена | R72: 1 | S72: 14000 | U72: 3200 | V72: =(P72*R72*S72)+(T72*U72*P72*R72) -> 14000 | W72: 0.09 | X72: =V72/(1-W72) -> 15384.615 | Y72: 0 | Z72: 0.09 | AA72: =Y72/(1-Z72) -> 0
B73: — прогрессивные переработки с 17 по 22 час | E73: 1 | F73: час | G73: 1 | J73: 6400 | K73: =(E73*G73*H73)+(I73*J73*E73*G73) -> 0 | L73: 0.09 | M73: =K73/(1-L73) -> 0 | P73: 1 | Q73: час | R73: 1 | U73: 6400 | V73: =(P73*R73*S73)+(T73*U73*P73*R73) -> 0 | W73: 0.09 | X73: =V73/(1-W73) -> 0 | Y73: 0 | Z73: 0.09 | AA73: =Y73/(1-Z73) -> 0
B74: — прогрессивные переработки с 23 часа | E74: 1 | F74: час | G74: 1 | J74: 12800 | K74: =(E74*G74*H74)+(I74*J74*E74*G74) -> 0 | L74: 0.09 | M74: =K74/(1-L74) -> 0 | P74: 1 | Q74: час | R74: 1 | U74: 12800 | V74: =(P74*R74*S74)+(T74*U74*P74*R74) -> 0 | W74: 0.09 | X74: =V74/(1-W74) -> 0 | Y74: 0 | Z74: 0.09 | AA74: =Y74/(1-Z74) -> 0
B75: Осветители и грипы | E75: 10 | F75: смена | G75: 1 | H75: 12000 | J75: 2600 | K75: =(E75*G75*H75)+(I75*J75*E75*G75) -> 120000 | L75: 0.09 | M75: =K75/(1-L75) -> 131868.13 | P75: 3 | Q75: смена | R75: 1 | S75: 12000 | U75: 2600 | V75: =(P75*R75*S75)+(T75*U75*P75*R75) -> 36000 | W75: 0.09 | X75: =V75/(1-W75) -> 39560.44 | Y75: 0 | Z75: 0.09 | AA75: =Y75/(1-Z75) -> 0
B76: — прогрессивные переработки с 17 по 22 час | E76: 8 | F76: час | G76: 1 | J76: 5200 | K76: =(E76*G76*H76)+(I76*J76*E76*G76) -> 0 | L76: 0.09 | M76: =K76/(1-L76) -> 0 | P76: 1 | Q76: час | R76: 1 | U76: 5200 | V76: =(P76*R76*S76)+(T76*U76*P76*R76) -> 0 | W76: 0.09 | X76: =V76/(1-W76) -> 0 | Y76: 0 | Z76: 0.09 | AA76: =Y76/(1-Z76) -> 0
B77: — прогрессивные переработки с 23 часа | E77: 1 | F77: час | G77: 1 | J77: 10400 | K77: =(E77*G77*H77)+(I77*J77*E77*G77) -> 0 | L77: 0.09 | M77: =K77/(1-L77) -> 0 | P77: 1 | Q77: час | R77: 1 | U77: 10400 | V77: =(P77*R77*S77)+(T77*U77*P77*R77) -> 0 | W77: 0.09 | X77: =V77/(1-W77) -> 0 | Y77: 0 | Z77: 0.09 | AA77: =Y77/(1-Z77) -> 0
B78: Техники долли | E78: 1 | F78: смена | G78: 1 | H78: 14000 | J78: 2900 | K78: =(E78*G78*H78)+(I78*J78*E78*G78) -> 14000 | L78: 0.09 | M78: =K78/(1-L78) -> 15384.615 | P78: 1 | Q78: смена | R78: 1 | S78: 14000 | U78: 2900 | V78: =(P78*R78*S78)+(T78*U78*P78*R78) -> 14000 | W78: 0.09 | X78: =V78/(1-W78) -> 15384.615 | Y78: 0 | Z78: 0.09 | AA78: =Y78/(1-Z78) -> 0
B79: — прогрессивные переработки с 17 по 22 час | E79: 1 | F79: час | G79: 1 | J79: 5800 | K79: =(E79*G79*H79)+(I79*J79*E79*G79) -> 0 | L79: 0.09 | M79: =K79/(1-L79) -> 0 | P79: 1 | Q79: час | R79: 1 | U79: 5800 | V79: =(P79*R79*S79)+(T79*U79*P79*R79) -> 0 | W79: 0.09 | X79: =V79/(1-W79) -> 0 | Y79: 0 | Z79: 0.09 | AA79: =Y79/(1-Z79) -> 0
B80: — прогрессивные переработки с 23 часа | E80: 1 | F80: час | G80: 1 | J80: 11600 | K80: =(E80*G80*H80)+(I80*J80*E80*G80) -> 0 | L80: 0.09 | M80: =K80/(1-L80) -> 0 | P80: 1 | Q80: час | R80: 1 | U80: 11600 | V80: =(P80*R80*S80)+(T80*U80*P80*R80) -> 0 | W80: 0.09 | X80: =V80/(1-W80) -> 0 | Y80: 0 | Z80: 0.09 | AA80: =Y80/(1-Z80) -> 0
B81: — погрузка/разгрузка | E81: 1 | F81: смена | G81: 1 | H81: 11600 | K81: =(E81*G81*H81)+(I81*J81*E81*G81) -> 11600 | L81: 0.09 | M81: =K81/(1-L81) -> 12747.253 | P81: 1 | Q81: смена | R81: 1 | S81: 11600 | V81: =(P81*R81*S81)+(T81*U81*P81*R81) -> 11600 | W81: 0.09 | X81: =V81/(1-W81) -> 12747.253 | Y81: 0 | Z81: 0.09 | AA81: =Y81/(1-Z81) -> 0
B82: Пультовик | E82: 1 | F82: смена | G82: 1 | H82: 25000 | J82: 5000 | K82: =(E82*G82*H82)+(I82*J82*E82*G82) -> 25000 | L82: 0.09 | M82: =K82/(1-L82) -> 27472.527 | P82: 1 | Q82: смена | R82: 1 | S82: 25000 | U82: 5000 | V82: =(P82*R82*S82)+(T82*U82*P82*R82) -> 25000 | W82: 0.09 | X82: =V82/(1-W82) -> 27472.527 | Y82: 0 | Z82: 0.09 | AA82: =Y82/(1-Z82) -> 0
B83: — прогрессивные переработки с 17 по 22 час | E83: 1 | F83: час | G83: 1 | J83: 20000 | K83: =(E83*G83*H83)+(I83*J83*E83*G83) -> 0 | L83: 0.09 | M83: =K83/(1-L83) -> 0 | P83: 1 | Q83: час | R83: 1 | U83: 20000 | V83: =(P83*R83*S83)+(T83*U83*P83*R83) -> 0 | W83: 0.09 | X83: =V83/(1-W83) -> 0 | Y83: 0 | Z83: 0.09 | AA83: =Y83/(1-Z83) -> 0
B84: — прогрессивные переработки с 23 часа | E84: 1 | F84: час | G84: 1 | J84: 40000 | K84: =(E84*G84*H84)+(I84*J84*E84*G84) -> 0 | L84: 0.09 | M84: =K84/(1-L84) -> 0 | P84: 1 | Q84: час | R84: 1 | U84: 40000 | V84: =(P84*R84*S84)+(T84*U84*P84*R84) -> 0 | W84: 0.09 | X84: =V84/(1-W84) -> 0 | Y84: 0 | Z84: 0.09 | AA84: =Y84/(1-Z84) -> 0
B85: Оператор стедикама | E85: 1 | F85: смена | G85: 1 | H85: 70000 | J85: 14000 | K85: =(E85*G85*H85)+(I85*J85*E85*G85) -> 70000 | L85: 0.09 | M85: =K85/(1-L85) -> 76923.077 | P85: 1 | Q85: смена | R85: 1 | S85: 70000 | U85: 14000 | V85: =(P85*R85*S85)+(T85*U85*P85*R85) -> 70000 | W85: 0.09 | X85: =V85/(1-W85) -> 76923.077 | Y85: 0 | Z85: 0.09 | AA85: =Y85/(1-Z85) -> 0
B86: — прогрессивные переработки с 17 по 22 час | E86: 1 | F86: час | G86: 1 | K86: =(E86*G86*H86)+(I86*J86*E86*G86) -> 0 | L86: 0.09 | M86: =K86/(1-L86) -> 0 | P86: 1 | Q86: час | R86: 1 | V86: =(P86*R86*S86)+(T86*U86*P86*R86) -> 0 | W86: 0.09 | X86: =V86/(1-W86) -> 0 | Y86: 0 | Z86: 0.09 | AA86: =Y86/(1-Z86) -> 0
B87: — прогрессивные переработки с 23 часа | E87: 1 | F87: час | G87: 1 | K87: =(E87*G87*H87)+(I87*J87*E87*G87) -> 0 | L87: 0.09 | M87: =K87/(1-L87) -> 0 | P87: 1 | Q87: час | R87: 1 | V87: =(P87*R87*S87)+(T87*U87*P87*R87) -> 0 | W87: 0.09 | X87: =V87/(1-W87) -> 0 | Y87: 0 | Z87: 0.09 | AA87: =Y87/(1-Z87) -> 0
B88: Оператор гимбла | E88: 1 | F88: смена | G88: 1 | H88: 70000 | J88: 14000 | K88: =(E88*G88*H88)+(I88*J88*E88*G88) -> 70000 | L88: 0.09 | M88: =K88/(1-L88) -> 76923.077 | P88: 1 | Q88: смена | R88: 1 | S88: 70000 | U88: 14000 | V88: =(P88*R88*S88)+(T88*U88*P88*R88) -> 70000 | W88: 0.09 | X88: =V88/(1-W88) -> 76923.077 | Y88: 0 | Z88: 0.09 | AA88: =Y88/(1-Z88) -> 0
B89: — прогрессивные переработки с 19 по 24 час | E89: 1 | F89: час | G89: 1 | J89: 36400 | K89: =(E89*G89*H89)+(I89*J89*E89*G89) -> 0 | L89: 0.09 | M89: =K89/(1-L89) -> 0 | P89: 1 | Q89: час | R89: 1 | U89: 36400 | V89: =(P89*R89*S89)+(T89*U89*P89*R89) -> 0 | W89: 0.09 | X89: =V89/(1-W89) -> 0 | Y89: 0 | Z89: 0.09 | AA89: =Y89/(1-Z89) -> 0
B90: — прогрессивные переработки с 24 часа | E90: 1 | F90: час | G90: 1 | J90: 72800 | K90: =(E90*G90*H90)+(I90*J90*E90*G90) -> 0 | L90: 0.09 | M90: =K90/(1-L90) -> 0 | P90: 1 | Q90: час | R90: 1 | U90: 72800 | V90: =(P90*R90*S90)+(T90*U90*P90*R90) -> 0 | W90: 0.09 | X90: =V90/(1-W90) -> 0 | Y90: 0 | Z90: 0.09 | AA90: =Y90/(1-Z90) -> 0
B91: ЗВУКООПЕРАТОРСКАЯ ГРУППА
B92: Звукооператор | E92: 1 | F92: смена | G92: 1 | K92: =(E92*G92*H92)+(I92*J92*E92*G92) -> 0 | L92: 0.09 | M92: =K92/(1-L92) -> 0 | P92: 1 | Q92: смена | R92: 1 | V92: =(P92*R92*S92)+(T92*U92*P92*R92) -> 0 | W92: 0.09 | X92: =V92/(1-W92) -> 0 | Y92: 0 | Z92: 0.09 | AA92: =Y92/(1-Z92) -> 0
B93: Ассистент звукооператора | E93: 1 | F93: смена | G93: 1 | K93: =(E93*G93*H93)+(I93*J93*E93*G93) -> 0 | L93: 0.09 | M93: =K93/(1-L93) -> 0 | P93: 1 | Q93: смена | R93: 1 | V93: =(P93*R93*S93)+(T93*U93*P93*R93) -> 0 | W93: 0.09 | X93: =V93/(1-W93) -> 0 | Y93: 0 | Z93: 0.09 | AA93: =Y93/(1-Z93) -> 0
B94: ХУДОЖЕСТВЕННЫЙ ДЕПАРТАМЕНТ
B95: Художник-постановщик | E95: 1 | F95: проект | G95: 1 | H95: 300000 | K95: =(E95*G95*H95)+(I95*J95*E95*G95) -> 300000 | L95: 0.09 | M95: =K95/(1-L95) -> 329670.33 | P95: 1 | Q95: проект | R95: 1 | S95: 300000 | V95: =(P95*R95*S95)+(T95*U95*P95*R95) -> 300000 | W95: 0.09 | X95: =V95/(1-W95) -> 329670.33 | Y95: 0 | Z95: 0.09 | AA95: =Y95/(1-Z95) -> 0
B96: Декоратор | E96: 1 | F96: проект | G96: 1 | H96: 160000 | K96: =(E96*G96*H96)+(I96*J96*E96*G96) -> 160000 | L96: 0.09 | M96: =K96/(1-L96) -> 175824.18 | P96: 1 | Q96: проект | R96: 1 | S96: 160000 | V96: =(P96*R96*S96)+(T96*U96*P96*R96) -> 160000 | W96: 0.09 | X96: =V96/(1-W96) -> 175824.18 | Y96: 0 | Z96: 0.09 | AA96: =Y96/(1-Z96) -> 0
B97: Ассистент по реквизиту | E97: 1 | F97: проект | G97: 1 | H97: 140000 | K97: =(E97*G97*H97)+(I97*J97*E97*G97) -> 140000 | L97: 0.09 | M97: =K97/(1-L97) -> 153846.15 | P97: 1 | Q97: проект | R97: 1 | S97: 140000 | V97: =(P97*R97*S97)+(T97*U97*P97*R97) -> 140000 | W97: 0.09 | X97: =V97/(1-W97) -> 153846.15 | Y97: 0 | Z97: 0.09 | AA97: =Y97/(1-Z97) -> 0
B98: Реквизиторы | E98: 1 | F98: смена | G98: 1 | H98: 10000 | J98: 3000 | K98: =(E98*G98*H98)+(I98*J98*E98*G98) -> 10000 | L98: 0.09 | M98: =K98/(1-L98) -> 10989.011 | P98: 1 | Q98: смена | R98: 1 | S98: 10000 | U98: 3000 | V98: =(P98*R98*S98)+(T98*U98*P98*R98) -> 10000 | W98: 0.09 | X98: =V98/(1-W98) -> 10989.011 | Y98: 0 | Z98: 0.09 | AA98: =Y98/(1-Z98) -> 0
B99: Реквизиторы (закупка, застройка) | E99: 1 | F99: смена | G99: 1 | H99: 10000 | J99: 3000 | K99: =(E99*G99*H99)+(I99*J99*E99*G99) -> 10000 | L99: 0.09 | M99: =K99/(1-L99) -> 10989.011 | P99: 1 | Q99: смена | R99: 1 | S99: 10000 | U99: 3000 | V99: =(P99*R99*S99)+(T99*U99*P99*R99) -> 10000 | W99: 0.09 | X99: =V99/(1-W99) -> 10989.011 | Y99: 0 | Z99: 0.09 | AA99: =Y99/(1-Z99) -> 0
B100: Постановщики | E100: 1 | F100: смена | G100: 1 | H100: 10000 | J100: 3000 | K100: =(E100*G100*H100)+(I100*J100*E100*G100) -> 10000 | L100: 0.09 | M100: =K100/(1-L100) -> 10989.011 | P100: 1 | Q100: смена | R100: 1 | S100: 10000 | U100: 3000 | V100: =(P100*R100*S100)+(T100*U100*P100*R100) -> 10000 | W100: 0.09 | X100: =V100/(1-W100) -> 10989.011 | Y100: 0 | Z100: 0.09 | AA100: =Y100/(1-Z100) -> 0
B101: Постановщики (закупка, застройка) | E101: 1 | F101: смена | G101: 1 | H101: 10000 | J101: 3000 | K101: =(E101*G101*H101)+(I101*J101*E101*G101) -> 10000 | L101: 0.09 | M101: =K101/(1-L101) -> 10989.011 | P101: 1 | Q101: смена | R101: 1 | S101: 10000 | U101: 3000 | V101: =(P101*R101*S101)+(T101*U101*P101*R101) -> 10000 | W101: 0.09 | X101: =V101/(1-W101) -> 10989.011 | Y101: 0 | Z101: 0.09 | AA101: =Y101/(1-Z101) -> 0
B102: Художник по костюму (стилист) | E102: 1 | F102: проект | G102: 1 | K102: =(E102*G102*H102)+(I102*J102*E102*G102) -> 0 | L102: 0.09 | M102: =K102/(1-L102) -> 0 | P102: 1 | Q102: проект | R102: 1 | V102: =(P102*R102*S102)+(T102*U102*P102*R102) -> 0 | W102: 0.09 | X102: =V102/(1-W102) -> 0 | Y102: 0 | Z102: 0.09 | AA102: =Y102/(1-Z102) -> 0
B103: Ассистент художника по костюму | E103: 1 | F103: проект | G103: 1 | K103: =(E103*G103*H103)+(I103*J103*E103*G103) -> 0 | L103: 0.09 | M103: =K103/(1-L103) -> 0 | P103: 1 | Q103: проект | R103: 1 | V103: =(P103*R103*S103)+(T103*U103*P103*R103) -> 0 | W103: 0.09 | X103: =V103/(1-W103) -> 0 | Y103: 0 | Z103: 0.09 | AA103: =Y103/(1-Z103) -> 0
B104: ГРИМ И ВОЛОСЫ
B105: Художник по гриму (визажист) | E105: 1 | F105: смена | G105: 1 | K105: =(E105*G105*H105)+(I105*J105*E105*G105) -> 0 | L105: 0.09 | M105: =K105/(1-L105) -> 0 | P105: 1 | Q105: смена | R105: 1 | V105: =(P105*R105*S105)+(T105*U105*P105*R105) -> 0 | W105: 0.09 | X105: =V105/(1-W105) -> 0 | Y105: 0 | Z105: 0.09 | AA105: =Y105/(1-Z105) -> 0
...

Sheet CE (ИП)
K1: ИТОГО, ВКЛЮЧАЯ УСН И НДС | M1: =M281 -> 2639516.5 | O1: IN COST | P1: ЦЕЛЬ | R1: 0.2 | S1: МАРЖ–ТЬ (ПЛАН) | T1: =X284 -> 0.042889595 | U1: IN-COST (ПЛАН) | V1: =X276 -> 2223151.6 | X1: МАРЖ-ТЬ (ФАКТ) | Y1: =AA284 -> 1 | Z1: IN-COST (ФАКТ) | AA1: =AA279 -> 0
C2: Название проекта | E2: кол-во | F2: наименование единицы | G2: единица | H2: цена за единицу | I2: переработки (всего) | K2: подытог | L2: налоговая ставка | M2: итого c налогами | N2: комментарии | P2: кол-во | Q2: наименование единицы | R2: единица | S2: цена за единицу | T2: переработки (всего) | V2: подытог (ПЛАН) | W2: Налоговая ставка | X2: Итого c налогами (ПЛАН) | Y2: подытог (ФАКТ) | Z2: налог | AA2: Итого c налогами (ФАКТ)
A4: Съемочных дней | D4: 1 | I4: часы | J4: ставка | T4: часы | U4: ставка
A5: Съемочных часов | D5: 12
A7: A. РАЗРАБОТКА
B8: Разработка креатива | E8: 1 | F8: проект | G8: 1 | K8: =(E8*G8*H8)+(I8*J8*E8*G8) -> 0 | L8: 0.09 | M8: =K8/(1-L8) -> 0 | P8: 1 | Q8: проект | R8: 1 | V8: =(P8*R8*S8)+(T8*U8*P8*R8) -> 0 | W8: 0.09 | X8: =V8/(1-W8) -> 0 | Y8: 0 | Z8: 0.09 | AA8: =Y8/(1-Z8) -> 0
B9: Креативный супервайзинг проекта | E9: 1 | F9: проект | G9: 1 | K9: =(E9*G9*H9)+(I9*J9*E9*G9) -> 0 | L9: 0.09 | M9: =K9/(1-L9) -> 0 | P9: 1 | Q9: проект | R9: 1 | V9: =(P9*R9*S9)+(T9*U9*P9*R9) -> 0 | W9: 0.09 | X9: =V9/(1-W9) -> 0 | Y9: 0 | Z9: 0.09 | AA9: =Y9/(1-Z9) -> 0
B10: Директорс рисёрч | E10: 1 | F10: проект | G10: 1 | K10: =(E10*G10*H10)+(I10*J10*E10*G10) -> 0 | L10: 0.09 | M10: =K10/(1-L10) -> 0 | P10: 1 | Q10: проект | R10: 1 | S10: 30000 | V10: =(P10*R10*S10)+(T10*U10*P10*R10) -> 30000 | W10: 0.09 | X10: =V10/(1-W10) -> 32967.033 | Y10: 0 | Z10: 0.09 | AA10: =Y10/(1-Z10) -> 0
B11: Сценарий | E11: 1 | F11: проект | G11: 1 | K11: =(E11*G11*H11)+(I11*J11*E11*G11) -> 0 | L11: 0.09 | M11: =K11/(1-L11) -> 0 | P11: 1 | Q11: проект | R11: 1 | V11: =(P11*R11*S11)+(T11*U11*P11*R11) -> 0 | W11: 0.09 | X11: =V11/(1-W11) -> 0 | Y11: 0 | Z11: 0.09 | AA11: =Y11/(1-Z11) -> 0
B12: Раскадровка | E12: 1 | F12: кадр | G12: 1 | K12: =(E12*G12*H12)+(I12*J12*E12*G12) -> 0 | L12: 0.09 | M12: =K12/(1-L12) -> 0 | P12: 1 | Q12: кадр | R12: 1 | V12: =(P12*R12*S12)+(T12*U12*P12*R12) -> 0 | W12: 0.09 | X12: =V12/(1-W12) -> 0 | Y12: 0 | Z12: 0.09 | AA12: =Y12/(1-Z12) -> 0
B13: Аниматик | E13: 1 | F13: проект | G13: 1 | K13: =(E13*G13*H13)+(I13*J13*E13*G13) -> 0 | L13: 0.09 | M13: =K13/(1-L13) -> 0 | P13: 1 | Q13: проект | R13: 1 | V13: =(P13*R13*S13)+(T13*U13*P13*R13) -> 0 | W13: 0.09 | X13: =V13/(1-W13) -> 0 | Y13: 0 | Z13: 0.09 | AA13: =Y13/(1-Z13) -> 0
B14: ППМ-буклеты | E14: 1 | F14: проект | G14: 1 | K14: =(E14*G14*H14)+(I14*J14*E14*G14) -> 0 | L14: 0.09 | M14: =K14/(1-L14) -> 0 | P14: 1 | Q14: проект | R14: 1 | V14: =(P14*R14*S14)+(T14*U14*P14*R14) -> 0 | W14: 0.09 | X14: =V14/(1-W14) -> 0 | Y14: 0 | Z14: 0.09 | AA14: =Y14/(1-Z14) -> 0
B15: Переводчик | E15: 1 | F15: проект | G15: 1 | K15: =(E15*G15*H15)+(I15*J15*E15*G15) -> 0 | L15: 0.09 | M15: =K15/(1-L15) -> 0 | P15: 1 | Q15: проект | R15: 1 | V15: =(P15*R15*S15)+(T15*U15*P15*R15) -> 0 | W15: 0.09 | X15: =V15/(1-W15) -> 0 | Y15: 0 | Z15: 0.09 | AA15: =Y15/(1-Z15) -> 0
B16: Юридическое сопровождение | E16: 1 | F16: проект | G16: 1 | K16: =(E16*G16*H16)+(I16*J16*E16*G16) -> 0 | L16: 0.09 | M16: =K16/(1-L16) -> 0 | P16: 1 | Q16: проект | R16: 1 | V16: =(P16*R16*S16)+(T16*U16*P16*R16) -> 0 | W16: 0.09 | X16: =V16/(1-W16) -> 0 | Y16: 0 | Z16: 0.09 | AA16: =Y16/(1-Z16) -> 0
B17: Курьер, почтовые расходы | E17: 1 | F17: проект | G17: 1 | K17: =(E17*G17*H17)+(I17*J17*E17*G17) -> 0 | L17: 0.09 | M17: =K17/(1-L17) -> 0 | P17: 1 | Q17: проект | R17: 1 | V17: =(P17*R17*S17)+(T17*U17*P17*R17) -> 0 | W17: 0.09 | X17: =V17/(1-W17) -> 0 | Y17: 0 | Z17: 0.09 | AA17: =Y17/(1-Z17) -> 0
L18: ИТОГО РАЗРАБОТКА | M18: =SUM(M8:M17) -> 0 | W18: ИТОГО РАЗРАБОТКА | X18: =SUM(X8:X17) -> 32967.033 | Z18: ИТОГО РАЗРАБОТКА | AA18: =SUM(AA8:AA17) -> 0
A20: B. ПРЕДПРОИЗВОДСТВЕННАЯ ПОДГОТОВКА
B21: ПОДБОР ЛОКАЦИИ
B22: Локейшн-менеджер | E22: 1 | F22: проект | G22: 1 | K22: =(E22*G22*H22)+(I22*J22*E22*G22) -> 0 | L22: 0.09 | M22: =K22/(1-L22) -> 0 | P22: 1 | Q22: проект | R22: 1 | V22: =(P22*R22*S22)+(T22*U22*P22*R22) -> 0 | W22: 0.09 | X22: =V22/(1-W22) -> 0 | Y22: 0 | Z22: 0.09 | AA22: =Y22/(1-Z22) -> 0
B23: Микроавтобус | E23: 1 | F23: смена | G23: 1 | K23: =(E23*G23*H23)+(I23*J23*E23*G23) -> 0 | L23: 0.09 | M23: =K23/(1-L23) -> 0 | P23: 1 | Q23: смена | R23: 1 | V23: =(P23*R23*S23)+(T23*U23*P23*R23) -> 0 | W23: 0.09 | X23: =V23/(1-W23) -> 0 | Y23: 0 | Z23: 0.09 | AA23: =Y23/(1-Z23) -> 0
B24: КАСТИНГ
B25: Кастинг-директор | E25: 1 | F25: проект | G25: 1 | K25: =(E25*G25*H25)+(I25*J25*E25*G25) -> 0 | L25: 0.09 | M25: =K25/(1-L25) -> 0 | P25: 1 | Q25: проект | R25: 1 | V25: =(P25*R25*S25)+(T25*U25*P25*R25) -> 0 | W25: 0.09 | X25: =V25/(1-W25) -> 0 | Y25: 0 | Z25: 0.09 | AA25: =Y25/(1-Z25) -> 0
B26: Аренда студии | E26: 1 | F26: час | G26: 1 | K26: =(E26*G26*H26)+(I26*J26*E26*G26) -> 0 | L26: 0.09 | M26: =K26/(1-L26) -> 0 | P26: 1 | Q26: час | R26: 1 | V26: =(P26*R26*S26)+(T26*U26*P26*R26) -> 0 | W26: 0.09 | X26: =V26/(1-W26) -> 0 | Y26: 0 | Z26: 0.09 | AA26: =Y26/(1-Z26) -> 0
B27: Оператор | E27: 1 | F27: час | G27: 1 | K27: =(E27*G27*H27)+(I27*J27*E27*G27) -> 0 | L27: 0.09 | M27: =K27/(1-L27) -> 0 | P27: 1 | Q27: час | R27: 1 | V27: =(P27*R27*S27)+(T27*U27*P27*R27) -> 0 | W27: 0.09 | X27: =V27/(1-W27) -> 0 | Y27: 0 | Z27: 0.09 | AA27: =Y27/(1-Z27) -> 0
B28: Аренда съемочного оборудования | E28: 1 | F28: смена | G28: 1 | K28: =(E28*G28*H28)+(I28*J28*E28*G28) -> 0 | L28: 0.09 | M28: =K28/(1-L28) -> 0 | P28: 1 | Q28: смена | R28: 1 | V28: =(P28*R28*S28)+(T28*U28*P28*R28) -> 0 | W28: 0.09 | X28: =V28/(1-W28) -> 0 | Y28: 0 | Z28: 0.09 | AA28: =Y28/(1-Z28) -> 0
L29: ИТОГО ПРЕДПРОИЗВОДСТВЕННАЯ ПОДГОТОВКА | M29: =SUM(M22:M28) -> 0 | W29: ИТОГО ПРЕДПРОИЗВОДСТВЕННАЯ ПОДГОТОВКА | X29: =SUM(X22:X28) -> 0 | Z29: ИТОГО ПРЕДПРОИЗВОДСТВЕННАЯ ПОДГОТОВКА | AA29: =SUM(AA22:AA28) -> 0
A31: C. АКТЕРЫ
B32: Основной актер | E32: 1 | F32: смена | G32: 1 | K32: =(E32*G32*H32)+(I32*J32*E32*G32) -> 0 | L32: 0.09 | M32: =K32/(1-L32) -> 0 | P32: 1 | Q32: смена | R32: 1 | V32: =(P32*R32*S32)+(T32*U32*P32*R32) -> 0 | W32: 0.09 | X32: =V32/(1-W32) -> 0 | Y32: 0 | Z32: 0.09 | AA32: =Y32/(1-Z32) -> 0
B33: Второстепенный актер | E33: 1 | F33: смена | G33: 1 | K33: =(E33*G33*H33)+(I33*J33*E33*G33) -> 0 | L33: 0.09 | M33: =K33/(1-L33) -> 0 | P33: 1 | Q33: смена | R33: 1 | V33: =(P33*R33*S33)+(T33*U33*P33*R33) -> 0 | W33: 0.09 | X33: =V33/(1-W33) -> 0 | Y33: 0 | Z33: 0.09 | AA33: =Y33/(1-Z33) -> 0
B34: Массовка | E34: 1 | F34: смена | G34: 1 | K34: =(E34*G34*H34)+(I34*J34*E34*G34) -> 0 | L34: 0.09 | M34: =K34/(1-L34) -> 0 | P34: 1 | Q34: смена | R34: 1 | V34: =(P34*R34*S34)+(T34*U34*P34*R34) -> 0 | W34: 0.09 | X34: =V34/(1-W34) -> 0 | Y34: 0 | Z34: 0.09 | AA34: =Y34/(1-Z34) -> 0
B35: Ассистент по актерам | E35: 1 | F35: смена | G35: 1 | H35: 12000 | J35: 1500 | K35: =(E35*G35*H35)+(I35*J35*E35*G35) -> 12000 | L35: 0.09 | M35: =K35/(1-L35) -> 13186.813 | P35: 1 | Q35: смена | R35: 1 | S35: 12000 | U35: 1500 | V35: =(P35*R35*S35)+(T35*U35*P35*R35) -> 12000 | W35: 0.09 | X35: =V35/(1-W35) -> 13186.813 | Y35: 0 | Z35: 0.09 | AA35: =Y35/(1-Z35) -> 0
B36: Бригадир массовки (подбор + площадка) | E36: 1 | F36: смена | G36: 1 | K36: =(E36*G36*H36)+(I36*J36*E36*G36) -> 0 | L36: 0.09 | M36: =K36/(1-L36) -> 0 | P36: 1 | Q36: смена | R36: 1 | V36: =(P36*R36*S36)+(T36*U36*P36*R36) -> 0 | W36: 0.09 | X36: =V36/(1-W36) -> 0 | Y36: 0 | Z36: 0.09 | AA36: =Y36/(1-Z36) -> 0
L37: ИТОГО АКТЕРЫ | M37: =SUM(M32:M36) -> 13186.813 | W37: ИТОГО АКТЕРЫ | X37: =SUM(X32:X36) -> 13186.813 | Z37: ИТОГО АКТЕРЫ | AA37: =SUM(AA32:AA36) -> 0
A39: D. ГОНОРАРЫ
B40: ПРОДЮСЕРЫ И АДМИНИСТРАЦИЯ
B41: Исполнительный продюсер | E41: 1 | F41: проект | G41: 1 | H41: 200000 | K41: =(E41*G41*H41)+(I41*J41*E41*G41) -> 200000 | L41: 0.09 | M41: =K41/(1-L41) -> 219780.22 | P41: 1 | Q41: проект | R41: 1 | S41: 200000 | V41: =(P41*R41*S41)+(T41*U41*P41*R41) -> 200000 | W41: 0.09 | X41: =V41/(1-W41) -> 219780.22 | Y41: 0 | Z41: 0.09 | AA41: =Y41/(1-Z41) -> 0
B42: Линейный продюсер | E42: 1 | F42: проект | G42: 1 | K42: =(E42*G42*H42)+(I42*J42*E42*G42) -> 0 | L42: 0.09 | M42: =K42/(1-L42) -> 0 | P42: 1 | Q42: проект | R42: 1 | V42: =(P42*R42*S42)+(T42*U42*P42*R42) -> 0 | W42: 0.09 | X42: =V42/(1-W42) -> 0 | Y42: 0 | Z42: 0.09 | AA42: =Y42/(1-Z42) -> 0
B43: Ассистент продюсера | E43: 1 | F43: проект | G43: 1 | K43: =(E43*G43*H43)+(I43*J43*E43*G43) -> 0 | L43: 0.09 | M43: =K43/(1-L43) -> 0 | P43: 1 | Q43: проект | R43: 1 | V43: =(P43*R43*S43)+(T43*U43*P43*R43) -> 0 | W43: 0.09 | X43: =V43/(1-W43) -> 0 | Y43: 0 | Z43: 0.09 | AA43: =Y43/(1-Z43) -> 0
B44: Директор группы | E44: 1 | F44: проект | G44: 1 | H44: 150000 | K44: =(E44*G44*H44)+(I44*J44*E44*G44) -> 150000 | L44: 0.09 | M44: =K44/(1-L44) -> 164835.16 | P44: 1 | Q44: проект | R44: 1 | S44: 150000 | V44: =(P44*R44*S44)+(T44*U44*P44*R44) -> 150000 | W44: 0.09 | X44: =V44/(1-W44) -> 164835.16 | Y44: 0 | Z44: 0.09 | AA44: =Y44/(1-Z44) -> 0
B45: Заместитель директора | E45: 1 | F45: проект | G45: 1 | H45: 75000 | K45: =(E45*G45*H45)+(I45*J45*E45*G45) -> 75000 | L45: 0.09 | M45: =K45/(1-L45) -> 82417.582 | P45: 1 | Q45: проект | R45: 1 | S45: 75000 | V45: =(P45*R45*S45)+(T45*U45*P45*R45) -> 75000 | W45: 0.09 | X45: =V45/(1-W45) -> 82417.582 | Y45: 0 | Z45: 0.09 | AA45: =Y45/(1-Z45) -> 0
B46: Администратор | E46: 1 | F46: смена | G46: 1 | H46: 25000 | K46: =(E46*G46*H46)+(I46*J46*E46*G46) -> 25000 | L46: 0.09 | M46: =K46/(1-L46) -> 27472.527 | P46: 1 | Q46: смена | R46: 1 | S46: 25000 | V46: =(P46*R46*S46)+(T46*U46*P46*R46) -> 25000 | W46: 0.09 | X46: =V46/(1-W46) -> 27472.527 | Y46: 0 | Z46: 0.09 | AA46: =Y46/(1-Z46) -> 0
B47: Рабочие | E47: 1 | F47: смена | G47: 1 | H47: 7000 | J47: 700 | K47: =(E47*G47*H47)+(I47*J47*E47*G47) -> 7000 | L47: 0.09 | M47: =K47/(1-L47) -> 7692.3077 | P47: 1 | Q47: смена | R47: 1 | S47: 7000 | U47: 700 | V47: =(P47*R47*S47)+(T47*U47*P47*R47) -> 7000 | W47: 0.09 | X47: =V47/(1-W47) -> 7692.3077 | Y47: 0 | Z47: 0.09 | AA47: =Y47/(1-Z47) -> 0
B48: РЕЖИССЕРСКИЙ ДЕПАРТАМЕНТ
B49: Режиссер | E49: 1 | F49: проект | G49: 1 | K49: =(E49*G49*H49)+(I49*J49*E49*G49) -> 0 | L49: 0.09 | M49: =K49/(1-L49) -> 0 | P49: 1 | Q49: проект | R49: 1 | V49: =(P49*R49*S49)+(T49*U49*P49*R49) -> 0 | W49: 0.09 | X49: =V49/(1-W49) -> 0 | Y49: 0 | Z49: 0.09 | AA49: =Y49/(1-Z49) -> 0
B50: Второй режиссер | E50: 1 | F50: проект | G50: 1 | K50: =(E50*G50*H50)+(I50*J50*E50*G50) -> 0 | L50: 0.09 | M50: =K50/(1-L50) -> 0 | P50: 1 | Q50: проект | R50: 1 | V50: =(P50*R50*S50)+(T50*U50*P50*R50) -> 0 | W50: 0.09 | X50: =V50/(1-W50) -> 0 | Y50: 0 | Z50: 0.09 | AA50: =Y50/(1-Z50) -> 0
B51: Хлопушка | E51: 1 | F51: смена | G51: 1 | K51: =(E51*G51*H51)+(I51*J51*E51*G51) -> 0 | L51: 0.09 | M51: =K51/(1-L51) -> 0 | P51: 1 | Q51: смена | R51: 1 | V51: =(P51*R51*S51)+(T51*U51*P51*R51) -> 0 | W51: 0.09 | X51: =V51/(1-W51) -> 0 | Y51: 0 | Z51: 0.09 | AA51: =Y51/(1-Z51) -> 0
B52: Монтажер на площадке | E52: 1 | F52: час | G52: 1 | K52: =(E52*G52*H52)+(I52*J52*E52*G52) -> 0 | L52: 0.09 | M52: =K52/(1-L52) -> 0 | P52: 1 | Q52: час | R52: 1 | V52: =(P52*R52*S52)+(T52*U52*P52*R52) -> 0 | W52: 0.09 | X52: =V52/(1-W52) -> 0 | Y52: 0 | Z52: 0.09 | AA52: =Y52/(1-Z52) -> 0
B53: ОПЕРАТОРСКАЯ ГРУППА
B54: Оператор-постановщик | E54: 1 | F54: смена | G54: 1 | H54: 200000 | J54: 20000 | K54: =(E54*G54*H54)+(I54*J54*E54*G54) -> 200000 | L54: 0.09 | M54: =K54/(1-L54) -> 219780.22 | P54: 1 | Q54: смена | R54: 1 | S54: 200000 | U54: 20000 | V54: =(P54*R54*S54)+(T54*U54*P54*R54) -> 200000 | W54: 0.09 | X54: =V54/(1-W54) -> 219780.22 | Y54: 0 | Z54: 0.09 | AA54: =Y54/(1-Z54) -> 0
B55: — прогрессивные переработки с 17 по 22 час | E55: 1 | F55: час | G55: 1 | J55: 40000 | K55: =(E55*G55*H55)+(I55*J55*E55*G55) -> 0 | L55: 0.09 | M55: =K55/(1-L55) -> 0 | P55: 1 | Q55: час | R55: 1 | U55: 40000 | V55: =(P55*R55*S55)+(T55*U55*P55*R55) -> 0 | W55: 0.09 | X55: =V55/(1-W55) -> 0 | Y55: 0 | Z55: 0.09 | AA55: =Y55/(1-Z55) -> 0
B56: — прогрессивные переработки с 23 часа | E56: 1 | F56: час | G56: 1 | J56: 80000 | K56: =(E56*G56*H56)+(I56*J56*E56*G56) -> 0 | L56: 0.09 | M56: =K56/(1-L56) -> 0 | P56: 1 | Q56: час | R56: 1 | U56: 80000 | V56: =(P56*R56*S56)+(T56*U56*P56*R56) -> 0 | W56: 0.09 | X56: =V56/(1-W56) -> 0 | Y56: 0 | Z56: 0.09 | AA56: =Y56/(1-Z56) -> 0
B57: Фокус-пуллер | E57: 1 | F57: смена | G57: 1 | H57: 34000 | J57: 5000 | K57: =(E57*G57*H57)+(I57*J57*E57*G57) -> 34000 | L57: 0.09 | M57: =K57/(1-L57) -> 37362.637 | P57: 1 | Q57: смена | R57: 1 | S57: 34000 | U57: 5000 | V57: =(P57*R57*S57)+(T57*U57*P57*R57) -> 34000 | W57: 0.09 | X57: =V57/(1-W57) -> 37362.637 | Y57: 0 | Z57: 0.09 | AA57: =Y57/(1-Z57) -> 0
B58: — прогрессивные переработки с 17 по 22 час | E58: 1 | F58: час | G58: 1 | K58: =(E58*G58*H58)+(I58*J58*E58*G58) -> 0 | L58: 0.09 | M58: =K58/(1-L58) -> 0 | P58: 1 | Q58: час | R58: 1 | U58: 10000 | V58: =(P58*R58*S58)+(T58*U58*P58*R58) -> 0 | W58: 0.09 | X58: =V58/(1-W58) -> 0 | Y58: 0 | Z58: 0.09 | AA58: =Y58/(1-Z58) -> 0
B59: — прогрессивные переработки с 23 часа | E59: 1 | F59: час | G59: 1 | K59: =(E59*G59*H59)+(I59*J59*E59*G59) -> 0 | L59: 0.09 | M59: =K59/(1-L59) -> 0 | P59: 1 | Q59: час | R59: 1 | U59: 20000 | V59: =(P59*R59*S59)+(T59*U59*P59*R59) -> 0 | W59: 0.09 | X59: =V59/(1-W59) -> 0 | Y59: 0 | Z59: 0.09 | AA59: =Y59/(1-Z59) -> 0
B60: Механики камеры | E60: 1 | F60: смена | G60: 2 | H60: 18000 | J60: 3500 | K60: =(E60*G60*H60)+(I60*J60*E60*G60) -> 36000 | L60: 0.09 | M60: =K60/(1-L60) -> 39560.44 | P60: 1 | Q60: смена | R60: 2 | S60: 18000 | U60: 3500 | V60: =(P60*R60*S60)+(T60*U60*P60*R60) -> 36000 | W60: 0.09 | X60: =V60/(1-W60) -> 39560.44 | Y60: 0 | Z60: 0.09 | AA60: =Y60/(1-Z60) -> 0
B61: — прогрессивные переработки с 17 по 22 час | E61: 1 | F61: час | G61: 1 | J61: 7000 | K61: =(E61*G61*H61)+(I61*J61*E61*G61) -> 0 | L61: 0.09 | M61: =K61/(1-L61) -> 0 | P61: 1 | Q61: час | R61: 1 | U61: 7000 | V61: =(P61*R61*S61)+(T61*U61*P61*R61) -> 0 | W61: 0.09 | X61: =V61/(1-W61) -> 0 | Y61: 0 | Z61: 0.09 | AA61: =Y61/(1-Z61) -> 0
B62: — прогрессивные переработки с 23 часа | E62: 1 | F62: час | G62: 1 | J62: 14000 | K62: =(E62*G62*H62)+(I62*J62*E62*G62) -> 0 | L62: 0.09 | M62: =K62/(1-L62) -> 0 | P62: 1 | Q62: час | R62: 1 | U62: 14000 | V62: =(P62*R62*S62)+(T62*U62*P62*R62) -> 0 | W62: 0.09 | X62: =V62/(1-W62) -> 0 | Y62: 0 | Z62: 0.09 | AA62: =Y62/(1-Z62) -> 0
B63: — погрузка/разгрузка | E63: 1 | F63: смена | G63: 1 | H63: 14000 | K63: =(E63*G63*H63)+(I63*J63*E63*G63) -> 14000 | L63: 0.09 | M63: =K63/(1-L63) -> 15384.615 | P63: 1 | Q63: смена | R63: 1 | S63: 10000 | V63: =(P63*R63*S63)+(T63*U63*P63*R63) -> 10000 | W63: 0.09 | X63: =V63/(1-W63) -> 10989.011 | Y63: 0 | Z63: 0.09 | AA63: =Y63/(1-Z63) -> 0
B64: — расходники | E64: 1 | F64: смена | G64: 1 | H64: 3000 | K64: =(E64*G64*H64)+(I64*J64*E64*G64) -> 3000 | L64: 0.09 | M64: =K64/(1-L64) -> 3296.7033 | P64: 1 | Q64: смена | R64: 1 | S64: 3000 | V64: =(P64*R64*S64)+(T64*U64*P64*R64) -> 3000 | W64: 0.09 | X64: =V64/(1-W64) -> 3296.7033 | Y64: 0 | Z64: 0.09 | AA64: =Y64/(1-Z64) -> 0
B65: Гафер (освоение) | E65: 1 | F65: смена | G65: 1 | H65: 20000 | K65: =(E65*G65*H65)+(I65*J65*E65*G65) -> 20000 | L65: 0.09 | M65: =K65/(1-L65) -> 21978.022 | P65: 1 | Q65: смена | R65: 1 | S65: 20000 | V65: =(P65*R65*S65)+(T65*U65*P65*R65) -> 20000 | W65: 0.09 | X65: =V65/(1-W65) -> 21978.022 | Y65: 0 | Z65: 0.09 | AA65: =Y65/(1-Z65) -> 0
B66: Гафер | E66: 1 | F66: смена | G66: 1 | H66: 20000 | J66: 4000 | K66: =(E66*G66*H66)+(I66*J66*E66*G66) -> 20000 | L66: 0.09 | M66: =K66/(1-L66) -> 21978.022 | P66: 1 | Q66: смена | R66: 1 | S66: 20000 | U66: 4000 | V66: =(P66*R66*S66)+(T66*U66*P66*R66) -> 20000 | W66: 0.09 | X66: =V66/(1-W66) -> 21978.022 | Y66: 0 | Z66: 0.09 | AA66: =Y66/(1-Z66) -> 0
B67: — прогрессивные переработки с 17 по 22 час | E67: 1 | F67: час | G67: 1 | J67: 8000 | K67: =(E67*G67*H67)+(I67*J67*E67*G67) -> 0 | L67: 0.09 | M67: =K67/(1-L67) -> 0 | P67: 1 | Q67: час | R67: 1 | U67: 8000 | V67: =(P67*R67*S67)+(T67*U67*P67*R67) -> 0 | W67: 0.09 | X67: =V67/(1-W67) -> 0 | Y67: 0 | Z67: 0.09 | AA67: =Y67/(1-Z67) -> 0
B68: — прогрессивные переработки с 23 часа | E68: 1 | F68: час | G68: 1 | J68: 16000 | K68: =(E68*G68*H68)+(I68*J68*E68*G68) -> 0 | L68: 0.09 | M68: =K68/(1-L68) -> 0 | P68: 1 | Q68: час | R68: 1 | U68: 16000 | V68: =(P68*R68*S68)+(T68*U68*P68*R68) -> 0 | W68: 0.09 | X68: =V68/(1-W68) -> 0 | Y68: 0 | Z68: 0.09 | AA68: =Y68/(1-Z68) -> 0
B69: Кей-грип | E69: 1 | F69: смена | G69: 1 | H69: 14000 | J69: 3200 | K69: =(E69*G69*H69)+(I69*J69*E69*G69) -> 14000 | L69: 0.09 | M69: =K69/(1-L69) -> 15384.615 | P69: 1 | Q69: смена | R69: 1 | S69: 14000 | U69: 3200 | V69: =(P69*R69*S69)+(T69*U69*P69*R69) -> 14000 | W69: 0.09 | X69: =V69/(1-W69) -> 15384.615 | Y69: 0 | Z69: 0.09 | AA69: =Y69/(1-Z69) -> 0
B70: — прогрессивные переработки с 17 по 22 час | E70: 1 | F70: час | G70: 1 | J70: 6400 | K70: =(E70*G70*H70)+(I70*J70*E70*G70) -> 0 | L70: 0.09 | M70: =K70/(1-L70) -> 0 | P70: 1 | Q70: час | R70: 1 | U70: 6400 | V70: =(P70*R70*S70)+(T70*U70*P70*R70) -> 0 | W70: 0.09 | X70: =V70/(1-W70) -> 0 | Y70: 0 | Z70: 0.09 | AA70: =Y70/(1-Z70) -> 0
B71: — прогрессивные переработки с 23 часа | E71: 1 | F71: час | G71: 1 | J71: 12800 | K71: =(E71*G71*H71)+(I71*J71*E71*G71) -> 0 | L71: 0.09 | M71: =K71/(1-L71) -> 0 | P71: 1 | Q71: час | R71: 1 | U71: 12800 | V71: =(P71*R71*S71)+(T71*U71*P71*R71) -> 0 | W71: 0.09 | X71: =V71/(1-W71) -> 0 | Y71: 0 | Z71: 0.09 | AA71: =Y71/(1-Z71) -> 0
B72: Бест-бой | E72: 1 | F72: смена | G72: 1 | H72: 14000 | J72: 3200 | K72: =(E72*G72*H72)+(I72*J72*E72*G72) -> 14000 | L72: 0.09 | M72: =K72/(1-L72) -> 15384.615 | P72: 1 | Q72: смена | R72: 1 | S72: 14000 | U72: 3200 | V72: =(P72*R72*S72)+(T72*U72*P72*R72) -> 14000 | W72: 0.09 | X72: =V72/(1-W72) -> 15384.615 | Y72: 0 | Z72: 0.09 | AA72: =Y72/(1-Z72) -> 0
B73: — прогрессивные переработки с 17 по 22 час | E73: 1 | F73: час | G73: 1 | J73: 6400 | K73: =(E73*G73*H73)+(I73*J73*E73*G73) -> 0 | L73: 0.09 | M73: =K73/(1-L73) -> 0 | P73: 1 | Q73: час | R73: 1 | U73: 6400 | V73: =(P73*R73*S73)+(T73*U73*P73*R73) -> 0 | W73: 0.09 | X73: =V73/(1-W73) -> 0 | Y73: 0 | Z73: 0.09 | AA73: =Y73/(1-Z73) -> 0
B74: — прогрессивные переработки с 23 часа | E74: 1 | F74: час | G74: 1 | J74: 12800 | K74: =(E74*G74*H74)+(I74*J74*E74*G74) -> 0 | L74: 0.09 | M74: =K74/(1-L74) -> 0 | P74: 1 | Q74: час | R74: 1 | U74: 12800 | V74: =(P74*R74*S74)+(T74*U74*P74*R74) -> 0 | W74: 0.09 | X74: =V74/(1-W74) -> 0 | Y74: 0 | Z74: 0.09 | AA74: =Y74/(1-Z74) -> 0
B75: Осветители и грипы | E75: 10 | F75: смена | G75: 1 | H75: 12000 | J75: 2600 | K75: =(E75*G75*H75)+(I75*J75*E75*G75) -> 120000 | L75: 0.09 | M75: =K75/(1-L75) -> 131868.13 | P75: 10 | Q75: смена | R75: 1 | S75: 12000 | U75: 2600 | V75: =(P75*R75*S75)+(T75*U75*P75*R75) -> 120000 | W75: 0.09 | X75: =V75/(1-W75) -> 131868.13 | Y75: 0 | Z75: 0.09 | AA75: =Y75/(1-Z75) -> 0
B76: — прогрессивные переработки с 17 по 22 час | E76: 8 | F76: час | G76: 1 | J76: 5200 | K76: =(E76*G76*H76)+(I76*J76*E76*G76) -> 0 | L76: 0.09 | M76: =K76/(1-L76) -> 0 | P76: 8 | Q76: час | R76: 1 | U76: 5200 | V76: =(P76*R76*S76)+(T76*U76*P76*R76) -> 0 | W76: 0.09 | X76: =V76/(1-W76) -> 0 | Y76: 0 | Z76: 0.09 | AA76: =Y76/(1-Z76) -> 0
B77: — прогрессивные переработки с 23 часа | E77: 1 | F77: час | G77: 1 | J77: 10400 | K77: =(E77*G77*H77)+(I77*J77*E77*G77) -> 0 | L77: 0.09 | M77: =K77/(1-L77) -> 0 | P77: 1 | Q77: час | R77: 1 | U77: 10400 | V77: =(P77*R77*S77)+(T77*U77*P77*R77) -> 0 | W77: 0.09 | X77: =V77/(1-W77) -> 0 | Y77: 0 | Z77: 0.09 | AA77: =Y77/(1-Z77) -> 0
B78: Техники долли | E78: 1 | F78: смена | G78: 1 | H78: 14000 | J78: 2900 | K78: =(E78*G78*H78)+(I78*J78*E78*G78) -> 14000 | L78: 0.09 | M78: =K78/(1-L78) -> 15384.615 | P78: 1 | Q78: смена | R78: 1 | S78: 14000 | U78: 2900 | V78: =(P78*R78*S78)+(T78*U78*P78*R78) -> 14000 | W78: 0.09 | X78: =V78/(1-W78) -> 15384.615 | Y78: 0 | Z78: 0.09 | AA78: =Y78/(1-Z78) -> 0
B79: — прогрессивные переработки с 17 по 22 час | E79: 1 | F79: час | G79: 1 | J79: 5800 | K79: =(E79*G79*H79)+(I79*J79*E79*G79) -> 0 | L79: 0.09 | M79: =K79/(1-L79) -> 0 | P79: 1 | Q79: час | R79: 1 | U79: 5800 | V79: =(P79*R79*S79)+(T79*U79*P79*R79) -> 0 | W79: 0.09 | X79: =V79/(1-W79) -> 0 | Y79: 0 | Z79: 0.09 | AA79: =Y79/(1-Z79) -> 0
B80: — прогрессивные переработки с 23 часа | E80: 1 | F80: час | G80: 1 | J80: 11600 | K80: =(E80*G80*H80)+(I80*J80*E80*G80) -> 0 | L80: 0.09 | M80: =K80/(1-L80) -> 0 | P80: 1 | Q80: час | R80: 1 | U80: 11600 | V80: =(P80*R80*S80)+(T80*U80*P80*R80) -> 0 | W80: 0.09 | X80: =V80/(1-W80) -> 0 | Y80: 0 | Z80: 0.09 | AA80: =Y80/(1-Z80) -> 0
B81: — погрузка/разгрузка | E81: 1 | F81: смена | G81: 1 | H81: 11600 | K81: =(E81*G81*H81)+(I81*J81*E81*G81) -> 11600 | L81: 0.09 | M81: =K81/(1-L81) -> 12747.253 | P81: 1 | Q81: смена | R81: 1 | S81: 11600 | V81: =(P81*R81*S81)+(T81*U81*P81*R81) -> 11600 | W81: 0.09 | X81: =V81/(1-W81) -> 12747.253 | Y81: 0 | Z81: 0.09 | AA81: =Y81/(1-Z81) -> 0
B82: Пультовик | E82: 1 | F82: смена | G82: 1 | H82: 25000 | J82: 5000 | K82: =(E82*G82*H82)+(I82*J82*E82*G82) -> 25000 | L82: 0.09 | M82: =K82/(1-L82) -> 27472.527 | P82: 1 | Q82: смена | R82: 1 | S82: 25000 | U82: 5000 | V82: =(P82*R82*S82)+(T82*U82*P82*R82) -> 25000 | W82: 0.09 | X82: =V82/(1-W82) -> 27472.527 | Y82: 0 | Z82: 0.09 | AA82: =Y82/(1-Z82) -> 0
B83: — прогрессивные переработки с 17 по 22 час | E83: 1 | F83: час | G83: 1 | J83: 20000 | K83: =(E83*G83*H83)+(I83*J83*E83*G83) -> 0 | L83: 0.09 | M83: =K83/(1-L83) -> 0 | P83: 1 | Q83: час | R83: 1 | U83: 20000 | V83: =(P83*R83*S83)+(T83*U83*P83*R83) -> 0 | W83: 0.09 | X83: =V83/(1-W83) -> 0 | Y83: 0 | Z83: 0.09 | AA83: =Y83/(1-Z83) -> 0
B84: — прогрессивные переработки с 23 часа | E84: 1 | F84: час | G84: 1 | J84: 12800 | K84: =(E84*G84*H84)+(I84*J84*E84*G84) -> 0 | L84: 0.09 | M84: =K84/(1-L84) -> 0 | P84: 1 | Q84: час | R84: 1 | U84: 40000 | V84: =(P84*R84*S84)+(T84*U84*P84*R84) -> 0 | W84: 0.09 | X84: =V84/(1-W84) -> 0 | Y84: 0 | Z84: 0.09 | AA84: =Y84/(1-Z84) -> 0
B85: Оператор стедикама | E85: 1 | F85: смена | G85: 1 | H85: 70000 | J85: 14000 | K85: =(E85*G85*H85)+(I85*J85*E85*G85) -> 70000 | L85: 0.09 | P85: 1 | Q85: смена | R85: 1 | S85: 70000 | U85: 14000 | V85: =(P85*R85*S85)+(T85*U85*P85*R85) -> 70000 | W85: 0.09 | X85: =V85/(1-W85) -> 76923.077 | Y85: 0 | Z85: 0.09 | AA85: =Y85/(1-Z85) -> 0
B86: — прогрессивные переработки с 17 по 22 час | E86: 1 | F86: час | G86: 1 | K86: =(E86*G86*H86)+(I86*J86*E86*G86) -> 0 | L86: 0.09 | P86: 1 | Q86: час | R86: 1 | V86: =(P86*R86*S86)+(T86*U86*P86*R86) -> 0 | W86: 0.09 | X86: =V86/(1-W86) -> 0 | Y86: 0 | Z86: 0.09 | AA86: =Y86/(1-Z86) -> 0
B87: — прогрессивные переработки с 23 часа | E87: 1 | F87: час | G87: 1 | K87: =(E87*G87*H87)+(I87*J87*E87*G87) -> 0 | L87: 0.09 | P87: 1 | Q87: час | R87: 1 | V87: =(P87*R87*S87)+(T87*U87*P87*R87) -> 0 | W87: 0.09 | X87: =V87/(1-W87) -> 0 | Y87: 0 | Z87: 0.09 | AA87: =Y87/(1-Z87) -> 0
B88: Оператор гимбла | E88: 1 | F88: смена | G88: 1 | H88: 70000 | J88: 14000 | K88: =(E88*G88*H88)+(I88*J88*E88*G88) -> 70000 | L88: 0.09 | M88: =K88/(1-L88) -> 76923.077 | P88: 1 | Q88: смена | R88: 1 | S88: 70000 | U88: 14000 | V88: =(P88*R88*S88)+(T88*U88*P88*R88) -> 70000 | W88: 0.09 | X88: =V88/(1-W88) -> 76923.077 | Y88: 0 | Z88: 0.09 | AA88: =Y88/(1-Z88) -> 0
B89: — прогрессивные переработки с 19 по 24 час | E89: 1 | F89: час | G89: 1 | K89: =(E89*G89*H89)+(I89*J89*E89*G89) -> 0 | L89: 0.09 | M89: =K89/(1-L89) -> 0 | P89: 1 | Q89: час | R89: 1 | U89: 36400 | V89: =(P89*R89*S89)+(T89*U89*P89*R89) -> 0 | W89: 0.09 | X89: =V89/(1-W89) -> 0 | Y89: 0 | Z89: 0.09 | AA89: =Y89/(1-Z89) -> 0
B90: — прогрессивные переработки с 24 часа | E90: 1 | F90: час | G90: 1 | K90: =(E90*G90*H90)+(I90*J90*E90*G90) -> 0 | L90: 0.09 | M90: =K90/(1-L90) -> 0 | P90: 1 | Q90: час | R90: 1 | U90: 72800 | V90: =(P90*R90*S90)+(T90*U90*P90*R90) -> 0 | W90: 0.09 | X90: =V90/(1-W90) -> 0 | Y90: 0 | Z90: 0.09 | AA90: =Y90/(1-Z90) -> 0
B91: ЗВУКООПЕРАТОРСКАЯ ГРУППА
B92: Звукооператор | E92: 1 | F92: смена | G92: 1 | K92: =(E92*G92*H92)+(I92*J92*E92*G92) -> 0 | L92: 0.09 | M92: =K92/(1-L92) -> 0 | P92: 1 | Q92: смена | R92: 1 | V92: =(P92*R92*S92)+(T92*U92*P92*R92) -> 0 | W92: 0.09 | X92: =V92/(1-W92) -> 0 | Y92: 0 | Z92: 0.09 | AA92: =Y92/(1-Z92) -> 0
B93: Ассистент звукооператора | E93: 1 | F93: смена | G93: 1 | K93: =(E93*G93*H93)+(I93*J93*E93*G93) -> 0 | L93: 0.09 | M93: =K93/(1-L93) -> 0 | P93: 1 | Q93: смена | R93: 1 | V93: =(P93*R93*S93)+(T93*U93*P93*R93) -> 0 | W93: 0.09 | X93: =V93/(1-W93) -> 0 | Y93: 0 | Z93: 0.09 | AA93: =Y93/(1-Z93) -> 0
B94: ХУДОЖЕСТВЕННЫЙ ДЕПАРТАМЕНТ
B95: Художник-постановщик | E95: 1 | F95: проект | G95: 1 | H95: 300000 | K95: =(E95*G95*H95)+(I95*J95*E95*G95) -> 300000 | L95: 0.09 | M95: =K95/(1-L95) -> 329670.33 | P95: 1 | Q95: проект | R95: 1 | S95: 300000 | V95: =(P95*R95*S95)+(T95*U95*P95*R95) -> 300000 | W95: 0.09 | X95: =V95/(1-W95) -> 329670.33 | Y95: 0 | Z95: 0.09 | AA95: =Y95/(1-Z95) -> 0
B96: Декоратор | E96: 1 | F96: проект | G96: 1 | H96: 160000 | K96: =(E96*G96*H96)+(I96*J96*E96*G96) -> 160000 | L96: 0.09 | M96: =K96/(1-L96) -> 175824.18 | P96: 1 | Q96: проект | R96: 1 | S96: 160000 | V96: =(P96*R96*S96)+(T96*U96*P96*R96) -> 160000 | W96: 0.09 | X96: =V96/(1-W96) -> 175824.18 | Y96: 0 | Z96: 0.09 | AA96: =Y96/(1-Z96) -> 0
B97: Ассистент по реквизиту | E97: 1 | F97: проект | G97: 1 | H97: 140000 | K97: =(E97*G97*H97)+(I97*J97*E97*G97) -> 140000 | L97: 0.09 | M97: =K97/(1-L97) -> 153846.15 | P97: 1 | Q97: проект | R97: 1 | S97: 140000 | V97: =(P97*R97*S97)+(T97*U97*P97*R97) -> 140000 | W97: 0.09 | X97: =V97/(1-W97) -> 153846.15 | Y97: 0 | Z97: 0.09 | AA97: =Y97/(1-Z97) -> 0
B98: Реквизиторы | E98: 1 | F98: смена | G98: 1 | H98: 10000 | J98: 3000 | K98: =(E98*G98*H98)+(I98*J98*E98*G98) -> 10000 | L98: 0.09 | M98: =K98/(1-L98) -> 10989.011 | P98: 1 | Q98: смена | R98: 1 | S98: 10000 | U98: 2000 | V98: =(P98*R98*S98)+(T98*U98*P98*R98) -> 10000 | W98: 0.09 | X98: =V98/(1-W98) -> 10989.011 | Y98: 0 | Z98: 0.09 | AA98: =Y98/(1-Z98) -> 0
B99: Реквизиторы (закупка, застройка) | E99: 1 | F99: смена | G99: 1 | H99: 10000 | J99: 3000 | K99: =(E99*G99*H99)+(I99*J99*E99*G99) -> 10000 | L99: 0.09 | M99: =K99/(1-L99) -> 10989.011 | P99: 1 | Q99: смена | R99: 1 | S99: 10000 | U99: 2000 | V99: =(P99*R99*S99)+(T99*U99*P99*R99) -> 10000 | W99: 0.09 | X99: =V99/(1-W99) -> 10989.011 | Y99: 0 | Z99: 0.09 | AA99: =Y99/(1-Z99) -> 0
B100: Постановщики | E100: 1 | F100: смена | G100: 1 | H100: 10000 | J100: 3000 | K100: =(E100*G100*H100)+(I100*J100*E100*G100) -> 10000 | L100: 0.09 | M100: =K100/(1-L100) -> 10989.011 | P100: 1 | Q100: смена | R100: 1 | S100: 10000 | U100: 2000 | V100: =(P100*R100*S100)+(T100*U100*P100*R100) -> 10000 | W100: 0.09 | X100: =V100/(1-W100) -> 10989.011 | Y100: 0 | Z100: 0.09 | AA100: =Y100/(1-Z100) -> 0
B101: Постановщики (закупка, застройка) | E101: 1 | F101: смена | G101: 1 | H101: 10000 | J101: 3000 | K101: =(E101*G101*H101)+(I101*J101*E101*G101) -> 10000 | L101: 0.09 | M101: =K101/(1-L101) -> 10989.011 | P101: 1 | Q101: смена | R101: 1 | S101: 10000 | U101: 2000 | V101: =(P101*R101*S101)+(T101*U101*P101*R101) -> 10000 | W101: 0.09 | X101: =V101/(1-W101) -> 10989.011 | Y101: 0 | Z101: 0.09 | AA101: =Y101/(1-Z101) -> 0
B102: Художник по костюму (стилист) | E102: 1 | F102: проект | G102: 1 | K102: =(E102*G102*H102)+(I102*J102*E102*G102) -> 0 | L102: 0.09 | M102: =K102/(1-L102) -> 0 | P102: 1 | Q102: проект | R102: 1 | V102: =(P102*R102*S102)+(T102*U102*P102*R102) -> 0 | W102: 0.09 | X102: =V102/(1-W102) -> 0 | Y102: 0 | Z102: 0.09 | AA102: =Y102/(1-Z102) -> 0
B103: Ассистент художника по костюму | E103: 1 | F103: проект | G103: 1 | K103: =(E103*G103*H103)+(I103*J103*E103*G103) -> 0 | L103: 0.09 | M103: =K103/(1-L103) -> 0 | P103: 1 | Q103: проект | R103: 1 | V103: =(P103*R103*S103)+(T103*U103*P103*R103) -> 0 | W103: 0.09 | X103: =V103/(1-W103) -> 0 | Y103: 0 | Z103: 0.09 | AA103: =Y103/(1-Z103) -> 0
B104: ГРИМ И ВОЛОСЫ
B105: Художник по гриму (визажист) | E105: 1 | F105: смена | G105: 1 | K105: =(E105*G105*H105)+(I105*J105*E105*G105) -> 0 | L105: 0.09 | M105: =K105/(1-L105) -> 0 | P105: 1 | Q105: смена | R105: 1 | V105: =(P105*R105*S105)+(T105*U105*P105*R105) -> 0 | W105: 0.09 | X105: =V105/(1-W105) -> 0 | Y105: 0 | Z105: 0.09 | AA105: =Y105/(1-Z105) -> 0
...

Sheet PASSPORT (ООО)
A1: ФИНАНСЫ И ДОКУМЕНТЫ – КЛИЕНТ
A2: Название проекта
A3: Наше юр лицо | B3: ООО "Культ"
A4: Юр лицо клиента
A5: Продюсер
A6: План IN-cost GROSS (с налогами) | B6: ='CE (ООО)'!X279 -> 2198649
A7: Факт IN-cost GROSS (с налогами) | B7: ='CE (ООО)'!AA279 -> 94678.665
A8: OUT-cost NET (без НДС) | B8: ='CE (ООО)'!M279 -> 2582186.2
A9: OUT-cost GROSS (с НДС) | B9: ='CE (ООО)'!M281 -> 3150267.2
A10: Плановая маржинальность (%) | B10: =(B8-B6)/B8 -> 0.14853198
A11: Фактическая маржинальность (%) | B11: ='CE (ООО)'!AA284 -> 0.96333391
A12: Финансовые условия: сроки и условия оплаты (сумма / пред- и постоплата / до какого числа каждая оплата)
A13: Ссылка на смету
A14: Папка проекта
A15: Видеоролики
A16: Дата съемки
A17: Дата сдачи результатов работ (выставления акта)
A18: Конкретный подробный перечень услуг / виды работ
A19: Сроки начала и окончания работ
A20: Количество основных версий роликов
A21: Хронометраж каждой основной версии роликов
A22: Количество монтажных версий роликов
A23: Хронометраж каждой монтажной версии роликов
... A64: Прописать возможность использования роликов в нашем портфолио, сайте, соц сетях (для нас и команды)?

Sheet PASSPORT (ИП)
A1: ФИНАНСЫ И ДОКУМЕНТЫ – КЛИЕНТ
A2: Название проекта
A3: Наше юр лицо | B3: ИП Мельников
A4: Юр лицо клиента
A5: Продюсер
A6: План IN-cost GROSS (с налогами) | B6: ='CE (ИП)'!X279 -> 2223151.6
A7: Факт IN-cost GROSS (с налогами) | B7: ='CE (ИП)'!AA279 -> 0
A8: OUT-cost GROSS (с налогами ИП) | B8: ='CE (ИП)'!M281 -> 2639516.5
A9: Плановая маржинальность (%) | B9: ='CE (ИП)'!T1 -> 0.042889595
A10: Фактическая маржинальность (%) | B10: ='CE (ИП)'!AA284 -> 1
A11: Финансовые условия: сроки и условия оплаты (сумма / пред- и постоплата / до какого числа каждая оплата)
A12: Ссылка на смету
A13: Папка проекта
A14: Видеоролики
A15: Дата съемки
A16: Дата сдачи результатов работ (выставления акта)
A17: Конкретный подробный перечень услуг / виды работ
A18: Сроки начала и окончания работ
A19: Количество основных версий роликов
A20: Хронометраж каждой основной версии роликов
A21: Количество монтажных версий роликов
A22: Хронометраж каждой монтажной версии роликов
... A63: Прописать возможность использования роликов в нашем портфолио, сайте, соц сетях (для нас и команды)?

Sheet PASSPORT (допкост) (ООО)
A1: ФИНАНСЫ И ДОКУМЕНТЫ – КЛИЕНТ
A2: План IN-cost GROSS (с налогами) | B2: ='CE (ООО)'!X279 -> 2198649
A3: Факт IN-cost GROSS (с налогами) | B3: ='CE (ООО)'!AA279 -> 94678.665
A4: OUT-cost NET (без НДС) | B4: ='CE (ООО)'!M279 -> 2582186.2
A5: OUT-cost GROSS (с НДС) | B5: ='CE (ООО)'!M281 -> 3150267.2
A6: Плановая маржинальность (%) | B6: =(B4-B2)/B4 -> 0.14853198
A7: Фактическая маржинальность (%) | B7: ='CE (ООО)'!AA284 -> 0.96333391
A8: Финансовые условия: сроки и условия оплаты (сумма / пред- и постоплата / до какого числа каждая оплата)
A9: Конкретный подробный перечень доп услуг / виды доп работ
A10: Сроки начала и окончания доп работ
A11: РИД. Какие РИД создавались?
A12: - новые РИД не возникают
A13: - актеры
A14: - диктор
A15: - компьютерная графика
A16: Музыка:
A17: - композитор (если да, сколько пишет треков и каким хронометражем)
A18: - стоковая
A19: Объем прав:
... A44: - территория

Sheet PASSPORT (допкост) (ИП)
A1: ФИНАНСЫ И ДОКУМЕНТЫ – КЛИЕНТ
A2: План IN-cost GROSS (с налогами) | B2: ='CE (ИП)'!X279 -> 2223151.6
A3: Факт IN-cost GROSS (с налогами) | B3: ='CE (ИП)'!AA279 -> 0
A4: OUT-cost NET (без НДС) | B4: ='CE (ИП)'!M279 -> 2322774.5
A5: OUT-cost GROSS (с НДС) | B5: ='CE (ИП)'!M281 -> 2639516.5
A6: Плановая маржинальность (%) | B6: =(B4-B2)/B4 -> 0.042889595
A7: Фактическая маржинальность (%) | B7: ='CE (ИП)'!AA284 -> 1
A8: Финансовые условия: сроки и условия оплаты (сумма / пред- и постоплата / до какого числа каждая оплата)
A9: Конкретный подробный перечень доп услуг / виды доп работ
A10: Сроки начала и окончания доп работ
A11: РИД. Какие РИД создавались?
A12: - новые РИД не возникают
A13: - актеры
A14: - диктор
A15: - компьютерная графика
A16: Музыка:
A17: - композитор (если да, сколько пишет треков и каким хронометражем)
A18: - стоковая
A19: Объем прав:
... A44: - территория

Sheet ПЕРЕРАБОТКИ
A1: РАСЧЕТ ПЕРЕРАБОТОК | B1: Смена | C1: Вызов до мотора: режиссер, второй режиссер, оператор и фокус | D1: Вызов до мотора и выход: механики и остальной тех. персонал | E1: Вызов до мотора и выход: бригада осветителей и постановщиков | F1: Текущий обед | G1: За МКАД
B2: 12 | C2: 0 | D2: 3 | E2: 4 | F2: 1 | G2: 0
A5: наименование единицы | B5: смена/час | C5: переработки | G5: всего часов переработки
C6: часы | D6: вызов до смены | E6: текущий обед | F6: за МКАД
A7: Режиссер | B7: 16 | C7: =B2-B7 -> -4 | D7: =C2 -> 0 | E7: =F2 -> 1 | F7: =G2 -> 0 | G7: =C7+D7+E7+F7 -> -3
A8: Второй режиссер | B8: 16 | C8: =B2-B8 -> -4 | D8: =C2 -> 0 | E8: =F2 -> 1 | F8: =G2 -> 0 | G8: =C8+D8+E8+F8 -> -3
A9: Оператор-постановщик | B9: 12 | C9: =B2-B9 -> 0 | D9: =C2 -> 0 | E9: =F2 -> 1 | F9: =G2 -> 0 | G9: =C9+D9+E9+F9 -> 1
A11: Фокус-пуллер | B11: 10 | C11: =B2-B11 -> 2 | D11: =C2 -> 0 | E11: =F2 -> 1 | F11: =G2 -> 0 | G11: =C11+D11+E11+F11 -> 3
A12: Механики камеры | B12: 10 | C12: =B2-B12 -> 2 | D12: =D2 -> 3 | E12: =F2 -> 1 | F12: =G2 -> 0 | G12: =C12+D12+E12+F12 -> 6
A13: Бригада осветителей | B13: 10 | C13: =B2-B13 -> 2 | D13: =E2 -> 4 | E13: =F2 -> 1 | F13: =G2 -> 0 | G13: =C13+D13+E13+F13 -> 7
A14: Механики долли/крана | B14: 10 | C14: =B2-B14 -> 2 | D14: =D2 -> 3 | E14: =F2 -> 1 | F14: =G2 -> 0 | G14: =C14+D14+E14+F14 -> 6
A15: Стедикам/гимбл/дрон | B15: 8 | C15: =B2-B15 -> 4 | D15: =D2 -> 3 | E15: =F2 -> 1 | F15: =G2 -> 0 | G15: =C15+D15+E15+F15 -> 8
A16: Motion Control | B16: 8 | C16: =B2-B16 -> 4 | D16: =D2 -> 3 | E16: =F2 -> 1 | F16: =G2 -> 0 | G16: =C16+D16+E16+F16 -> 8
A18: Звукорежиссер/Гример/Ассистент | B18: 10 | C18: =B2-B18 -> 2 | D18: =D2 -> 3 | E18: =F2 -> 1 | F18: =G2 -> 0 | G18: =C18+D18+E18+F18 -> 6
A19: Реквизитор/постановщик | B19: 8 | C19: =B2-B19 -> 4 | D19: =E2 -> 4 | E19: =F9 -> 0 | F19: =G2 -> 0 | G19: =C19+D19+E19+F19 -> 8
A20: SFX/VFX | B20: 10 | C20: =B2-B20 -> 2 | D20: =D2 -> 3 | E20: =F2 -> 1 | F20: =G2 -> 0 | G20: =C20+D20+E20+F20 -> 6
A22: Аренда локации | B22: 12 | C22: =B2-B22 -> 0 | D22: =E2 -> 4 | E22: 0 | F22: 0 | G22: =C22+D22+E22+F22 -> 4
A23: Транспорт (светобаза, гриптрак, гена и т.д.) | B23: 10 | C23: =B2-B23 -> 2 | D23: =E2 -> 4 | E23: 0 | F23: =G2 -> 0 | G23: =C23+D23+E23+F23 -> 6
A24: Транспорт (камерваген, гримваген и т.д.) | B24: 10 | C24: =B2-B24 -> 2 | D24: =D2 -> 3 | E24: =F2 -> 1 | F24: =G2 -> 0 | G24: =C24+D24+E24+F24 -> 6
